Workbook

Sheet Ассортимент
A1: TMFF — стартовый ассортимент
A2: Синим — данные AliExpress (варианты лотов собраны в Chrome 25.09.2026, конструкторы — из поиска aliexpress.com), чёрным — формулы, жёлтым — проверить. Цена — за товар, без платной доставки, если она есть. У конструкторов с aliexpress.com жёлтая цена — верхняя оценка: реальная может быть до двух раз ниже.
A3: Повторы убраны: болид + пилот + ливрея + масштаб встречаются один раз, по самой низкой цене. Другие лоты с тем же вариантом — в «Запасной лот». «Вариант на Ali» — что выбрать при заказе.
A4: Раздел | B4: Название на сайте | C4: Масштаб | D4: Цена на Ali, ₽ | E4: Наша цена, ₽ | F4: Прибыль с шт., ₽ | G4: Болид | H4: Пилот | I4: Ливрея / версия | J4: Год | K4: Заказов лота | L4: Рейтинг | M4: Лот | N4: Вариант на Ali | O4: Запасной лот · цена | P4: Повтор? | Q4: Лимит 1:24 | R4: Заметки и что проверить
A5: Модели 1:43 — сезон 2025 | B5: Red Bull RB21 — Цунода #22 | C5: 1:43 | D5: 789 | E5: =IF(D5="","",IF(D5<Параметры!$B$4,CEILING(D5*Параметры!$B$5,100)-10,IF(D5<=Параметры!$B$6,CEILING(D5*Параметры!$B$7,100)-10,CEILING(D5*Параметры!$B$8,100)-10))) -> 1590 | F5: =IF(D5="","",ROUND(E5*(1-Параметры!$B$9-Параметры!$B$10-Параметры!$B$11)-D5,0)) -> 570 | G5: Red Bull RB21 | H5: Цунода #22 | I5: стандартная | J5: 2025 | K5: 1947 | L5: 4.9 | M5: открыть | N5: 22-TSU-Bahrain | O5: 755468 · 879 ₽ | P5: =IF(COUNTIFS($G$5:$G$66,G5,$H$5:$H$66,H5,$I$5:$I$66,I5,$C$5:$C$66,C5)>1,"повтор","") | Q5: =IF(C5<>"1:24","",IF(D5="","проверить",IF(D5<=Параметры!$B$12,"ок","дороже лимита")))
A6: Модели 1:43 — сезон 2025 | B6: Red Bull RB21 — Цунода #22, белая, ГП Японии | C6: 1:43 | D6: 789 | E6: =IF(D6="","",IF(D6<Параметры!$B$4,CEILING(D6*Параметры!$B$5,100)-10,IF(D6<=Параметры!$B$6,CEILING(D6*Параметры!$B$7,100)-10,CEILING(D6*Параметры!$B$8,100)-10))) -> 1590 | F6: =IF(D6="","",ROUND(E6*(1-Параметры!$B$9-Параметры!$B$10-Параметры!$B$11)-D6,0)) -> 570 | G6: Red Bull RB21 | H6: Цунода #22 | I6: белая, ГП Японии | J6: 2025 | K6: 1947 | L6: 4.9 | M6: открыть | N6: 22-TSU-Japan | O6: 755468 · 879 ₽ | P6: =IF(COUNTIFS($G$5:$G$66,G6,$H$5:$H$66,H6,$I$5:$I$66,I6,$C$5:$C$66,C6)>1,"повтор","") | Q6: =IF(C6<>"1:24","",IF(D6="","проверить",IF(D6<=Параметры!$B$12,"ок","дороже лимита"))) | R6: Белая ливрея в честь Honda (Сузука 2025). Обязательно в ассортименте.
A7: Модели 1:43 — сезон 2025 | B7: Red Bull RB21 — Ферстаппен #1 | C7: 1:43 | D7: 879 | E7: =IF(D7="","",IF(D7<Параметры!$B$4,CEILING(D7*Параметры!$B$5,100)-10,IF(D7<=Параметры!$B$6,CEILING(D7*Параметры!$B$7,100)-10,CEILING(D7*Параметры!$B$8,100)-10))) -> 1790 | F7: =IF(D7="","",ROUND(E7*(1-Параметры!$B$9-Параметры!$B$10-Параметры!$B$11)-D7,0)) -> 651 | G7: Red Bull RB21 | H7: Ферстаппен #1 | I7: стандартная | J7: 2025 | K7: 791 | L7: 4.9 | M7: открыть | N7: 2025 RB21-1BHR | P7: =IF(COUNTIFS($G$5:$G$66,G7,$H$5:$H$66,H7,$I$5:$I$66,I7,$C$5:$C$66,C7)>1,"повтор","") | Q7: =IF(C7<>"1:24","",IF(D7="","проверить",IF(D7<=Параметры!$B$12,"ок","дороже лимита")))
A8: Модели 1:43 — сезон 2025 | B8: Red Bull RB21 — Ферстаппен #1, белая, ГП Японии | C8: 1:43 | D8: 789 | E8: =IF(D8="","",IF(D8<Параметры!$B$4,CEILING(D8*Параметры!$B$5,100)-10,IF(D8<=Параметры!$B$6,CEILING(D8*Параметры!$B$7,100)-10,CEILING(D8*Параметры!$B$8,100)-10))) -> 1590 | F8: =IF(D8="","",ROUND(E8*(1-Параметры!$B$9-Параметры!$B$10-Параметры!$B$11)-D8,0)) -> 570 | G8: Red Bull RB21 | H8: Ферстаппен #1 | I8: белая, ГП Японии | J8: 2025 | K8: 1947 | L8: 4.9 | M8: открыть | N8: 1-VER-Japan | O8: 755468 · 879 ₽ | P8: =IF(COUNTIFS($G$5:$G$66,G8,$H$5:$H$66,H8,$I$5:$I$66,I8,$C$5:$C$66,C8)>1,"повтор","") | Q8: =IF(C8<>"1:24","",IF(D8="","проверить",IF(D8<=Параметры!$B$12,"ок","дороже лимита"))) | R8: Белая ливрея в честь Honda (Сузука 2025). Обязательно в ассортименте.
A9: Модели 1:43 — сезон 2025 | B9: Ferrari SF-25 — Хэмилтон #44 | C9: 1:43 | D9: 879 | E9: =IF(D9="","",IF(D9<Параметры!$B$4,CEILING(D9*Параметры!$B$5,100)-10,IF(D9<=Параметры!$B$6,CEILING(D9*Параметры!$B$7,100)-10,CEILING(D9*Параметры!$B$8,100)-10))) -> 1790 | F9: =IF(D9="","",ROUND(E9*(1-Параметры!$B$9-Параметры!$B$10-Параметры!$B$11)-D9,0)) -> 651 | G9: Ferrari SF-25 | H9: Хэмилтон #44 | I9: стандартная | J9: 2025 | K9: 791 | L9: 4.9 | M9: открыть | N9: 2025 SF25-44 | P9: =IF(COUNTIFS($G$5:$G$66,G9,$H$5:$H$66,H9,$I$5:$I$66,I9,$C$5:$C$66,C9)>1,"повтор","") | Q9: =IF(C9<>"1:24","",IF(D9="","проверить",IF(D9<=Параметры!$B$12,"ок","дороже лимита")))
A10: Модели 1:43 — сезон 2025 | B10: Ferrari SF-25 — Хэмилтон #44, ГП Майами | C10: 1:43 | D10: 789 | E10: =IF(D10="","",IF(D10<Параметры!$B$4,CEILING(D10*Параметры!$B$5,100)-10,IF(D10<=Параметры!$B$6,CEILING(D10*Параметры!$B$7,100)-10,CEILING(D10*Параметры!$B$8,100)-10))) -> 1590 | F10: =IF(D10="","",ROUND(E10*(1-Параметры!$B$9-Параметры!$B$10-Параметры!$B$11)-D10,0)) -> 570 | G10: Ferrari SF-25 | H10: Хэмилтон #44 | I10: ГП Майами | J10: 2025 | K10: 1947 | L10: 4.9 | M10: открыть | N10: 44-HAM-Miami | P10: =IF(COUNTIFS($G$5:$G$66,G10,$H$5:$H$66,H10,$I$5:$I$66,I10,$C$5:$C$66,C10)>1,"повтор","") | Q10: =IF(C10<>"1:24","",IF(D10="","проверить",IF(D10<=Параметры!$B$12,"ок","дороже лимита"))) | R10: Спецливрея Ferrari на Гран-при Майами.
A11: Модели 1:43 — сезон 2025 | B11: Ferrari SF-25 — Леклер #16 | C11: 1:43 | D11: 789 | E11: =IF(D11="","",IF(D11<Параметры!$B$4,CEILING(D11*Параметры!$B$5,100)-10,IF(D11<=Параметры!$B$6,CEILING(D11*Параметры!$B$7,100)-10,CEILING(D11*Параметры!$B$8,100)-10))) -> 1590 | F11: =IF(D11="","",ROUND(E11*(1-Параметры!$B$9-Параметры!$B$10-Параметры!$B$11)-D11,0)) -> 570 | G11: Ferrari SF-25 | H11: Леклер #16 | I11: стандартная | J11: 2025 | K11: 1947 | L11: 4.9 | M11: открыть | N11: 16-LEC | O11: 755468 · 879 ₽ | P11: =IF(COUNTIFS($G$5:$G$66,G11,$H$5:$H$66,H11,$I$5:$I$66,I11,$C$5:$C$66,C11)>1,"повтор","") | Q11: =IF(C11<>"1:24","",IF(D11="","проверить",IF(D11<=Параметры!$B$12,"ок","дороже лимита")))
A12: Модели 1:43 — сезон 2025 | B12: Ferrari SF-25 — Леклер #16, ГП Майами | C12: 1:43 | D12: 789 | E12: =IF(D12="","",IF(D12<Параметры!$B$4,CEILING(D12*Параметры!$B$5,100)-10,IF(D12<=Параметры!$B$6,CEILING(D12*Параметры!$B$7,100)-10,CEILING(D12*Параметры!$B$8,100)-10))) -> 1590 | F12: =IF(D12="","",ROUND(E12*(1-Параметры!$B$9-Параметры!$B$10-Параметры!$B$11)-D12,0)) -> 570 | G12: Ferrari SF-25 | H12: Леклер #16 | I12: ГП Майами | J12: 2025 | K12: 1947 | L12: 4.9 | M12: открыть | N12: 16-LEC-Miami | O12: 755468 · 879 ₽ | P12: =IF(COUNTIFS($G$5:$G$66,G12,$H$5:$H$66,H12,$I$5:$I$66,I12,$C$5:$C$66,C12)>1,"повтор","") | Q12: =IF(C12<>"1:24","",IF(D12="","проверить",IF(D12<=Параметры!$B$12,"ок","дороже лимита"))) | R12: Спецливрея Ferrari на Гран-при Майами.
A13: Модели 1:43 — сезон 2025 | B13: Mercedes W16 — Антонелли #12 | C13: 1:43 | D13: 879 | E13: =IF(D13="","",IF(D13<Параметры!$B$4,CEILING(D13*Параметры!$B$5,100)-10,IF(D13<=Параметры!$B$6,CEILING(D13*Параметры!$B$7,100)-10,CEILING(D13*Параметры!$B$8,100)-10))) -> 1790 | F13: =IF(D13="","",ROUND(E13*(1-Параметры!$B$9-Параметры!$B$10-Параметры!$B$11)-D13,0)) -> 651 | G13: Mercedes W16 | H13: Антонелли #12 | I13: стандартная | J13: 2025 | K13: 791 | L13: 4.9 | M13: открыть | N13: 2025 W16 E-12 | P13: =IF(COUNTIFS($G$5:$G$66,G13,$H$5:$H$66,H13,$I$5:$I$66,I13,$C$5:$C$66,C13)>1,"повтор","") | Q13: =IF(C13<>"1:24","",IF(D13="","проверить",IF(D13<=Параметры!$B$12,"ок","дороже лимита")))
A14: Модели 1:43 — сезон 2025 | B14: Mercedes W16 — Рассел #63 | C14: 1:43 | D14: 879 | E14: =IF(D14="","",IF(D14<Параметры!$B$4,CEILING(D14*Параметры!$B$5,100)-10,IF(D14<=Параметры!$B$6,CEILING(D14*Параметры!$B$7,100)-10,CEILING(D14*Параметры!$B$8,100)-10))) -> 1790 | F14: =IF(D14="","",ROUND(E14*(1-Параметры!$B$9-Параметры!$B$10-Параметры!$B$11)-D14,0)) -> 651 | G14: Mercedes W16 | H14: Рассел #63 | I14: стандартная | J14: 2025 | K14: 791 | L14: 4.9 | M14: открыть | N14: 2025 W16 E-63 | P14: =IF(COUNTIFS($G$5:$G$66,G14,$H$5:$H$66,H14,$I$5:$I$66,I14,$C$5:$C$66,C14)>1,"повтор","") | Q14: =IF(C14<>"1:24","",IF(D14="","проверить",IF(D14<=Параметры!$B$12,"ок","дороже лимита")))
A15: Модели 1:43 — сезон 2025 | B15: McLaren MCL39 — Норрис #4 | C15: 1:43 | D15: 879 | E15: =IF(D15="","",IF(D15<Параметры!$B$4,CEILING(D15*Параметры!$B$5,100)-10,IF(D15<=Параметры!$B$6,CEILING(D15*Параметры!$B$7,100)-10,CEILING(D15*Параметры!$B$8,100)-10))) -> 1790 | F15: =IF(D15="","",ROUND(E15*(1-Параметры!$B$9-Параметры!$B$10-Параметры!$B$11)-D15,0)) -> 651 | G15: McLaren MCL39 | H15: Норрис #4 | I15: стандартная | J15: 2025 | K15: 791 | L15: 4.9 | M15: открыть | N15: 2025 MCL39-4 | P15: =IF(COUNTIFS($G$5:$G$66,G15,$H$5:$H$66,H15,$I$5:$I$66,I15,$C$5:$C$66,C15)>1,"повтор","") | Q15: =IF(C15<>"1:24","",IF(D15="","проверить",IF(D15<=Параметры!$B$12,"ок","дороже лимита")))
A16: Модели 1:43 — сезон 2025 | B16: McLaren MCL39 — Пиастри #81 | C16: 1:43 | D16: 879 | E16: =IF(D16="","",IF(D16<Параметры!$B$4,CEILING(D16*Параметры!$B$5,100)-10,IF(D16<=Параметры!$B$6,CEILING(D16*Параметры!$B$7,100)-10,CEILING(D16*Параметры!$B$8,100)-10))) -> 1790 | F16: =IF(D16="","",ROUND(E16*(1-Параметры!$B$9-Параметры!$B$10-Параметры!$B$11)-D16,0)) -> 651 | G16: McLaren MCL39 | H16: Пиастри #81 | I16: стандартная | J16: 2025 | K16: 791 | L16: 4.9 | M16: открыть | N16: 2025 MCL39-81 | P16: =IF(COUNTIFS($G$5:$G$66,G16,$H$5:$H$66,H16,$I$5:$I$66,I16,$C$5:$C$66,C16)>1,"повтор","") | Q16: =IF(C16<>"1:24","",IF(D16="","проверить",IF(D16<=Параметры!$B$12,"ок","дороже лимита")))
A17: Модели 1:43 — сезон 2025 | B17: Aston Martin AMR25 — Алонсо #14 | C17: 1:43 | D17: 879 | E17: =IF(D17="","",IF(D17<Параметры!$B$4,CEILING(D17*Параметры!$B$5,100)-10,IF(D17<=Параметры!$B$6,CEILING(D17*Параметры!$B$7,100)-10,CEILING(D17*Параметры!$B$8,100)-10))) -> 1790 | F17: =IF(D17="","",ROUND(E17*(1-Параметры!$B$9-Параметры!$B$10-Параметры!$B$11)-D17,0)) -> 651 | G17: Aston Martin AMR25 | H17: Алонсо #14 | I17: стандартная | J17: 2025 | K17: 791 | L17: 4.9 | M17: открыть | N17: 2025 AMR25-14 | P17: =IF(COUNTIFS($G$5:$G$66,G17,$H$5:$H$66,H17,$I$5:$I$66,I17,$C$5:$C$66,C17)>1,"повтор","") | Q17: =IF(C17<>"1:24","",IF(D17="","проверить",IF(D17<=Параметры!$B$12,"ок","дороже лимита")))
A18: Модели 1:43 — сезон 2025 | B18: Aston Martin AMR25 — Стролл #18 | C18: 1:43 | D18: 879 | E18: =IF(D18="","",IF(D18<Параметры!$B$4,CEILING(D18*Параметры!$B$5,100)-10,IF(D18<=Параметры!$B$6,CEILING(D18*Параметры!$B$7,100)-10,CEILING(D18*Параметры!$B$8,100)-10))) -> 1790 | F18: =IF(D18="","",ROUND(E18*(1-Параметры!$B$9-Параметры!$B$10-Параметры!$B$11)-D18,0)) -> 651 | G18: Aston Martin AMR25 | H18: Стролл #18 | I18: стандартная | J18: 2025 | K18: 791 | L18: 4.9 | M18: открыть | N18: 2025 AMR25-18 | P18: =IF(COUNTIFS($G$5:$G$66,G18,$H$5:$H$66,H18,$I$5:$I$66,I18,$C$5:$C$66,C18)>1,"повтор","") | Q18: =IF(C18<>"1:24","",IF(D18="","проверить",IF(D18<=Параметры!$B$12,"ок","дороже лимита")))
A19: Модели 1:43 — сезон 2025 | B19: Alpine A525 — Колапинто #43, ГП Монако | C19: 1:43 | D19: 879 | E19: =IF(D19="","",IF(D19<Параметры!$B$4,CEILING(D19*Параметры!$B$5,100)-10,IF(D19<=Параметры!$B$6,CEILING(D19*Параметры!$B$7,100)-10,CEILING(D19*Параметры!$B$8,100)-10))) -> 1790 | F19: =IF(D19="","",ROUND(E19*(1-Параметры!$B$9-Параметры!$B$10-Параметры!$B$11)-D19,0)) -> 651 | G19: Alpine A525 | H19: Колапинто #43 | I19: ГП Монако | J19: 2025 | K19: 791 | L19: 4.9 | M19: открыть | N19: 2025 A525-43MC | P19: =IF(COUNTIFS($G$5:$G$66,G19,$H$5:$H$66,H19,$I$5:$I$66,I19,$C$5:$C$66,C19)>1,"повтор","") | Q19: =IF(C19<>"1:24","",IF(D19="","проверить",IF(D19<=Параметры!$B$12,"ок","дороже лимита"))) | R19: Другой версии Alpine в лотах нет.
A20: Модели 1:43 — сезон 2025 | B20: Alpine A525 — Гасли #10, ГП Монако | C20: 1:43 | D20: 879 | E20: =IF(D20="","",IF(D20<Параметры!$B$4,CEILING(D20*Параметры!$B$5,100)-10,IF(D20<=Параметры!$B$6,CEILING(D20*Параметры!$B$7,100)-10,CEILING(D20*Параметры!$B$8,100)-10))) -> 1790 | F20: =IF(D20="","",ROUND(E20*(1-Параметры!$B$9-Параметры!$B$10-Параметры!$B$11)-D20,0)) -> 651 | G20: Alpine A525 | H20: Гасли #10 | I20: ГП Монако | J20: 2025 | K20: 791 | L20: 4.9 | M20: открыть | N20: 2025 A525-10MC | P20: =IF(COUNTIFS($G$5:$G$66,G20,$H$5:$H$66,H20,$I$5:$I$66,I20,$C$5:$C$66,C20)>1,"повтор","") | Q20: =IF(C20<>"1:24","",IF(D20="","проверить",IF(D20<=Параметры!$B$12,"ок","дороже лимита"))) | R20: Другой версии Alpine в лотах нет.
A21: Модели 1:43 — новинки 2026 | B21: Ferrari SF-26 — Хэмилтон #44 · масштаб 1:43 | C21: 1:43 | D21: 1489 | E21: =IF(D21="","",IF(D21<Параметры!$B$4,CEILING(D21*Параметры!$B$5,100)-10,IF(D21<=Параметры!$B$6,CEILING(D21*Параметры!$B$7,100)-10,CEILING(D21*Параметры!$B$8,100)-10))) -> 2990 | F21: =IF(D21="","",ROUND(E21*(1-Параметры!$B$9-Параметры!$B$10-Параметры!$B$11)-D21,0)) -> 1067 | G21: Ferrari SF-26 | H21: Хэмилтон #44 | I21: стандартная | J21: 2026 | K21: 45 | M21: открыть | N21: 2026 SF26-44 | P21: =IF(COUNTIFS($G$5:$G$66,G21,$H$5:$H$66,H21,$I$5:$I$66,I21,$C$5:$C$66,C21)>1,"повтор","") | Q21: =IF(C21<>"1:24","",IF(D21="","проверить",IF(D21<=Параметры!$B$12,"ок","дороже лимита"))) | R21: Новинка 2026, оценок ещё нет. На сайте масштаб 1:43 — в названии: модель дороже сезона 2025.
A22: Модели 1:43 — новинки 2026 | B22: Ferrari SF-26 — Леклер #16 · масштаб 1:43 | C22: 1:43 | D22: 1489 | E22: =IF(D22="","",IF(D22<Параметры!$B$4,CEILING(D22*Параметры!$B$5,100)-10,IF(D22<=Параметры!$B$6,CEILING(D22*Параметры!$B$7,100)-10,CEILING(D22*Параметры!$B$8,100)-10))) -> 2990 | F22: =IF(D22="","",ROUND(E22*(1-Параметры!$B$9-Параметры!$B$10-Параметры!$B$11)-D22,0)) -> 1067 | G22: Ferrari SF-26 | H22: Леклер #16 | I22: стандартная | J22: 2026 | K22: 45 | M22: открыть | N22: 2026 SF26-16 | P22: =IF(COUNTIFS($G$5:$G$66,G22,$H$5:$H$66,H22,$I$5:$I$66,I22,$C$5:$C$66,C22)>1,"повтор","") | Q22: =IF(C22<>"1:24","",IF(D22="","проверить",IF(D22<=Параметры!$B$12,"ок","дороже лимита"))) | R22: Новинка 2026, оценок ещё нет. На сайте масштаб 1:43 — в названии: модель дороже сезона 2025.
A23: Модели 1:43 — новинки 2026 | B23: Mercedes W17 — Антонелли #12 · масштаб 1:43 | C23: 1:43 | D23: 1489 | E23: =IF(D23="","",IF(D23<Параметры!$B$4,CEILING(D23*Параметры!$B$5,100)-10,IF(D23<=Параметры!$B$6,CEILING(D23*Параметры!$B$7,100)-10,CEILING(D23*Параметры!$B$8,100)-10))) -> 2990 | F23: =IF(D23="","",ROUND(E23*(1-Параметры!$B$9-Параметры!$B$10-Параметры!$B$11)-D23,0)) -> 1067 | G23: Mercedes W17 | H23: Антонелли #12 | I23: стандартная | J23: 2026 | K23: 31 | M23: открыть | N23: 2026 W17-12 | P23: =IF(COUNTIFS($G$5:$G$66,G23,$H$5:$H$66,H23,$I$5:$I$66,I23,$C$5:$C$66,C23)>1,"повтор","") | Q23: =IF(C23<>"1:24","",IF(D23="","проверить",IF(D23<=Параметры!$B$12,"ок","дороже лимита"))) | R23: Новинка 2026, оценок ещё нет. На сайте масштаб 1:43 — в названии: модель дороже сезона 2025.
A24: Модели 1:43 — новинки 2026 | B24: Mercedes W17 — Рассел #63 · масштаб 1:43 | C24: 1:43 | D24: 1489 | E24: =IF(D24="","",IF(D24<Параметры!$B$4,CEILING(D24*Параметры!$B$5,100)-10,IF(D24<=Параметры!$B$6,CEILING(D24*Параметры!$B$7,100)-10,CEILING(D24*Параметры!$B$8,100)-10))) -> 2990 | F24: =IF(D24="","",ROUND(E24*(1-Параметры!$B$9-Параметры!$B$10-Параметры!$B$11)-D24,0)) -> 1067 | G24: Mercedes W17 | H24: Рассел #63 | I24: стандартная | J24: 2026 | K24: 31 | M24: открыть | N24: 2026 W17-63 | P24: =IF(COUNTIFS($G$5:$G$66,G24,$H$5:$H$66,H24,$I$5:$I$66,I24,$C$5:$C$66,C24)>1,"повтор","") | Q24: =IF(C24<>"1:24","",IF(D24="","проверить",IF(D24<=Параметры!$B$12,"ок","дороже лимита"))) | R24: Новинка 2026, оценок ещё нет. На сайте масштаб 1:43 — в названии: модель дороже сезона 2025.
A25: Модели 1:24 | B25: Red Bull RB19 — Ферстаппен #1, ГП США | C25: 1:24 | D25: 2682 | E25: =IF(D25="","",IF(D25<Параметры!$B$4,CEILING(D25*Параметры!$B$5,100)-10,IF(D25<=Параметры!$B$6,CEILING(D25*Параметры!$B$7,100)-10,CEILING(D25*Параметры!$B$8,100)-10))) -> 4290 | F25: =IF(D25="","",ROUND(E25*(1-Параметры!$B$9-Параметры!$B$10-Параметры!$B$11)-D25,0)) -> 986 | G25: Red Bull RB19 | H25: Ферстаппен #1 | I25: ГП США | J25: 2023 | K25: 653 | L25: 4.9 | M25: открыть | N25: 1-24 2023 RB19-1USA | P25: =IF(COUNTIFS($G$5:$G$66,G25,$H$5:$H$66,H25,$I$5:$I$66,I25,$C$5:$C$66,C25)>1,"повтор","") | Q25: =IF(C25<>"1:24","",IF(D25="","проверить",IF(D25<=Параметры!$B$12,"ок","дороже лимита"))) -> ок | R25: Спецливрея RB19, придуманная фанатами (Остин 2023).
A26: Модели 1:24 | B26: Red Bull RB20 — Перес #11 | C26: 1:24 | D26: 2312 | E26: =IF(D26="","",IF(D26<Параметры!$B$4,CEILING(D26*Параметры!$B$5,100)-10,IF(D26<=Параметры!$B$6,CEILING(D26*Параметры!$B$7,100)-10,CEILING(D26*Параметры!$B$8,100)-10))) -> 3690 | F26: =IF(D26="","",ROUND(E26*(1-Параметры!$B$9-Параметры!$B$10-Параметры!$B$11)-D26,0)) -> 843 | G26: Red Bull RB20 | H26: Перес #11 | I26: стандартная | J26: 2024 | K26: 651 | L26: 4.9 | M26: открыть | N26: 1-24 2024 RB20-11 | O26: 502926 · 2409 ₽; 158416 · 2439 ₽ | P26: =IF(COUNTIFS($G$5:$G$66,G26,$H$5:$H$66,H26,$I$5:$I$66,I26,$C$5:$C$66,C26)>1,"повтор","") | Q26: =IF(C26<>"1:24","",IF(D26="","проверить",IF(D26<=Параметры!$B$12,"ок","дороже лимита"))) -> ок
A27: Модели 1:24 | B27: Red Bull RB20 — Ферстаппен #1 | C27: 1:24 | D27: 2409 | E27: =IF(D27="","",IF(D27<Параметры!$B$4,CEILING(D27*Параметры!$B$5,100)-10,IF(D27<=Параметры!$B$6,CEILING(D27*Параметры!$B$7,100)-10,CEILING(D27*Параметры!$B$8,100)-10))) -> 3890 | F27: =IF(D27="","",ROUND(E27*(1-Параметры!$B$9-Параметры!$B$10-Параметры!$B$11)-D27,0)) -> 917 | G27: Red Bull RB20 | H27: Ферстаппен #1 | I27: стандартная | J27: 2024 | K27: 78 | L27: 4.9 | M27: открыть | N27: 1-24 2024 RB20-1 | O27: 001375 · 2522 ₽; 158416 · 2659 ₽ | P27: =IF(COUNTIFS($G$5:$G$66,G27,$H$5:$H$66,H27,$I$5:$I$66,I27,$C$5:$C$66,C27)>1,"повтор","") | Q27: =IF(C27<>"1:24","",IF(D27="","проверить",IF(D27<=Параметры!$B$12,"ок","дороже лимита"))) -> ок
A28: Модели 1:24 | B28: Ferrari SF-24 — Леклер #16 | C28: 1:24 | D28: 2421 | E28: =IF(D28="","",IF(D28<Параметры!$B$4,CEILING(D28*Параметры!$B$5,100)-10,IF(D28<=Параметры!$B$6,CEILING(D28*Параметры!$B$7,100)-10,CEILING(D28*Параметры!$B$8,100)-10))) -> 3890 | F28: =IF(D28="","",ROUND(E28*(1-Параметры!$B$9-Параметры!$B$10-Параметры!$B$11)-D28,0)) -> 905 | G28: Ferrari SF-24 | H28: Леклер #16 | I28: стандартная | J28: 2024 | K28: 78 | L28: 4.9 | M28: открыть | N28: 1-24 2024 SF24-16 | O28: 158416 · 2461 ₽; 001375 · 2542 ₽ | P28: =IF(COUNTIFS($G$5:$G$66,G28,$H$5:$H$66,H28,$I$5:$I$66,I28,$C$5:$C$66,C28)>1,"повтор","") | Q28: =IF(C28<>"1:24","",IF(D28="","проверить",IF(D28<=Параметры!$B$12,"ок","дороже лимита"))) -> ок
A29: Модели 1:24 | B29: Ferrari SF-24 — Леклер #16, с надписью Leclerc | C29: 1:24 | D29: 2679 | E29: =IF(D29="","",IF(D29<Параметры!$B$4,CEILING(D29*Параметры!$B$5,100)-10,IF(D29<=Параметры!$B$6,CEILING(D29*Параметры!$B$7,100)-10,CEILING(D29*Параметры!$B$8,100)-10))) -> 4290 | F29: =IF(D29="","",ROUND(E29*(1-Параметры!$B$9-Параметры!$B$10-Параметры!$B$11)-D29,0)) -> 989 | G29: Ferrari SF-24 | H29: Леклер #16 | I29: с надписью Leclerc | J29: 2024 | K29: 653 | L29: 4.9 | M29: открыть | N29: 1-24 2024 SF24-161 | P29: =IF(COUNTIFS($G$5:$G$66,G29,$H$5:$H$66,H29,$I$5:$I$66,I29,$C$5:$C$66,C29)>1,"повтор","") | Q29: =IF(C29<>"1:24","",IF(D29="","проверить",IF(D29<=Параметры!$B$12,"ок","дороже лимита"))) -> ок | R29: Вариант «SF24-161» — версия с надписью Leclerc. Обычный SF-24 Леклера — отдельной строкой.
A30: Модели 1:24 | B30: Ferrari SF-24 — Сайнс #55 | C30: 1:24 | D30: 2439 | E30: =IF(D30="","",IF(D30<Параметры!$B$4,CEILING(D30*Параметры!$B$5,100)-10,IF(D30<=Параметры!$B$6,CEILING(D30*Параметры!$B$7,100)-10,CEILING(D30*Параметры!$B$8,100)-10))) -> 3990 | F30: =IF(D30="","",ROUND(E30*(1-Параметры!$B$9-Параметры!$B$10-Параметры!$B$11)-D30,0)) -> 972 | G30: Ferrari SF-24 | H30: Сайнс #55 | I30: стандартная | J30: 2024 | K30: 78 | L30: 4.9 | M30: открыть | N30: 1-24 2024 SF24-55 | P30: =IF(COUNTIFS($G$5:$G$66,G30,$H$5:$H$66,H30,$I$5:$I$66,I30,$C$5:$C$66,C30)>1,"повтор","") | Q30: =IF(C30<>"1:24","",IF(D30="","проверить",IF(D30<=Параметры!$B$12,"ок","дороже лимита"))) -> ок
A31: Модели 1:24 | B31: Mercedes W15 — Хэмилтон #44 | C31: 1:24 | D31: 2509 | E31: =IF(D31="","",IF(D31<Параметры!$B$4,CEILING(D31*Параметры!$B$5,100)-10,IF(D31<=Параметры!$B$6,CEILING(D31*Параметры!$B$7,100)-10,CEILING(D31*Параметры!$B$8,100)-10))) -> 4090 | F31: =IF(D31="","",ROUND(E31*(1-Параметры!$B$9-Параметры!$B$10-Параметры!$B$11)-D31,0)) -> 988 | G31: Mercedes W15 | H31: Хэмилтон #44 | I31: стандартная | J31: 2024 | K31: 651 | L31: 4.9 | M31: открыть | N31: 1-24 2024 W15-44 | O31: 502926 · 2611 ₽; 158416 · 2649 ₽ | P31: =IF(COUNTIFS($G$5:$G$66,G31,$H$5:$H$66,H31,$I$5:$I$66,I31,$C$5:$C$66,C31)>1,"повтор","") | Q31: =IF(C31<>"1:24","",IF(D31="","проверить",IF(D31<=Параметры!$B$12,"ок","дороже лимита"))) -> ок
A32: Модели 1:24 | B32: Mercedes W15 — Рассел #63 | C32: 1:24 | D32: 2509 | E32: =IF(D32="","",IF(D32<Параметры!$B$4,CEILING(D32*Параметры!$B$5,100)-10,IF(D32<=Параметры!$B$6,CEILING(D32*Параметры!$B$7,100)-10,CEILING(D32*Параметры!$B$8,100)-10))) -> 4090 | F32: =IF(D32="","",ROUND(E32*(1-Параметры!$B$9-Параметры!$B$10-Параметры!$B$11)-D32,0)) -> 988 | G32: Mercedes W15 | H32: Рассел #63 | I32: стандартная | J32: 2024 | K32: 651 | L32: 4.9 | M32: открыть | N32: 1-24 2024 W15-63 | P32: =IF(COUNTIFS($G$5:$G$66,G32,$H$5:$H$66,H32,$I$5:$I$66,I32,$C$5:$C$66,C32)>1,"повтор","") | Q32: =IF(C32<>"1:24","",IF(D32="","проверить",IF(D32<=Параметры!$B$12,"ок","дороже лимита"))) -> ок
A33: Модели 1:24 | B33: McLaren MCL38 — Норрис #4 | C33: 1:24 | D33: 1842 | E33: =IF(D33="","",IF(D33<Параметры!$B$4,CEILING(D33*Параметры!$B$5,100)-10,IF(D33<=Параметры!$B$6,CEILING(D33*Параметры!$B$7,100)-10,CEILING(D33*Параметры!$B$8,100)-10))) -> 2990 | F33: =IF(D33="","",ROUND(E33*(1-Параметры!$B$9-Параметры!$B$10-Параметры!$B$11)-D33,0)) -> 714 | G33: McLaren MCL38 | H33: Норрис #4 | I33: стандартная | J33: 2024 | K33: 150 | L33: 5 | M33: открыть | N33: Норрис #4 — выбрать в лоте | O33: 009441469506 · 2 699 ₽ | P33: =IF(COUNTIFS($G$5:$G$66,G33,$H$5:$H$66,H33,$I$5:$I$66,I33,$C$5:$C$66,C33)>1,"повтор","") | Q33: =IF(C33<>"1:24","",IF(D33="","проверить",IF(D33<=Параметры!$B$12,"ок","дороже лимита"))) -> ок | R33: Лот найден поиском aliexpress.ru, в CSV из Chrome его нет: проверить по фото, что ливрея обычная, а не «Майами», и цену варианта. Запасной: 1005009441469506 · 2 699 ₽, 503 заказа, 4.9.
A34: Модели 1:24 | B34: McLaren MCL38 — Пиастри #81 | C34: 1:24 | D34: 2549 | E34: =IF(D34="","",IF(D34<Параметры!$B$4,CEILING(D34*Параметры!$B$5,100)-10,IF(D34<=Параметры!$B$6,CEILING(D34*Параметры!$B$7,100)-10,CEILING(D34*Параметры!$B$8,100)-10))) -> 4090 | F34: =IF(D34="","",ROUND(E34*(1-Параметры!$B$9-Параметры!$B$10-Параметры!$B$11)-D34,0)) -> 948 | G34: McLaren MCL38 | H34: Пиастри #81 | I34: стандартная | J34: 2024 | K34: 651 | L34: 4.9 | M34: открыть | N34: 1-24 2024 MCL38-81 | P34: =IF(COUNTIFS($G$5:$G$66,G34,$H$5:$H$66,H34,$I$5:$I$66,I34,$C$5:$C$66,C34)>1,"повтор","") | Q34: =IF(C34<>"1:24","",IF(D34="","проверить",IF(D34<=Параметры!$B$12,"ок","дороже лимита"))) -> ок
A35: Модели 1:24 | B35: Aston Martin AMR25 — Алонсо #14 | C35: 1:24 | D35: 2631 | E35: =IF(D35="","",IF(D35<Параметры!$B$4,CEILING(D35*Параметры!$B$5,100)-10,IF(D35<=Параметры!$B$6,CEILING(D35*Параметры!$B$7,100)-10,CEILING(D35*Параметры!$B$8,100)-10))) -> 4290 | F35: =IF(D35="","",ROUND(E35*(1-Параметры!$B$9-Параметры!$B$10-Параметры!$B$11)-D35,0)) -> 1037 | G35: Aston Martin AMR25 | H35: Алонсо #14 | I35: стандартная | J35: 2025 | K35: 78 | L35: 4.9 | M35: открыть | N35: 1-24 2025 AMR25-14 | P35: =IF(COUNTIFS($G$5:$G$66,G35,$H$5:$H$66,H35,$I$5:$I$66,I35,$C$5:$C$66,C35)>1,"повтор","") | Q35: =IF(C35<>"1:24","",IF(D35="","проверить",IF(D35<=Параметры!$B$12,"ок","дороже лимита"))) -> ок
A36: Модели 1:24 | B36: Aston Martin AMR25 — Стролл #18 | C36: 1:24 | D36: 2401 | E36: =IF(D36="","",IF(D36<Параметры!$B$4,CEILING(D36*Параметры!$B$5,100)-10,IF(D36<=Параметры!$B$6,CEILING(D36*Параметры!$B$7,100)-10,CEILING(D36*Параметры!$B$8,100)-10))) -> 3890 | F36: =IF(D36="","",ROUND(E36*(1-Параметры!$B$9-Параметры!$B$10-Параметры!$B$11)-D36,0)) -> 925 | G36: Aston Martin AMR25 | H36: Стролл #18 | I36: стандартная | J36: 2025 | K36: 78 | L36: 4.9 | M36: открыть | N36: 1-24 2025 AMR25-18 | O36: 158416 · 2430 ₽; 001375 · 2522 ₽ | P36: =IF(COUNTIFS($G$5:$G$66,G36,$H$5:$H$66,H36,$I$5:$I$66,I36,$C$5:$C$66,C36)>1,"повтор","") | Q36: =IF(C36<>"1:24","",IF(D36="","проверить",IF(D36<=Параметры!$B$12,"ок","дороже лимита"))) -> ок
A37: Конструкторы — лицензия CaDA | B37: CaDA BWT Alpine A525 | C37: 1:24 | D37: 4524 | E37: =IF(D37="","",IF(D37<Параметры!$B$4,CEILING(D37*Параметры!$B$5,100)-10,IF(D37<=Параметры!$B$6,CEILING(D37*Параметры!$B$7,100)-10,CEILING(D37*Параметры!$B$8,100)-10))) -> 7290 | F37: =IF(D37="","",ROUND(E37*(1-Параметры!$B$9-Параметры!$B$10-Параметры!$B$11)-D37,0)) -> 1709 | G37: Alpine A525 | H37: — | I37: CaDA | J37: 2025 | K37: 268 | L37: 4.9 | M37: открыть | N37: проверить | P37: =IF(COUNTIFS($G$5:$G$66,G37,$H$5:$H$66,H37,$I$5:$I$66,I37,$C$5:$C$66,C37)>1,"повтор","") | Q37: =IF(C37<>"1:24","",IF(D37="","проверить",IF(D37<=Параметры!$B$12,"ок","дороже лимита"))) -> дороже лимита | R37: Официальная лицензия Alpine. Цена — верхняя оценка (зачёркнутая цена), реальная может быть до двух раз ниже. Вариант «с коробкой» и его цену не проверяли: в CSV из Chrome этого лота нет.
A38: Конструкторы — лицензия CaDA | B38: CaDA Kick Sauber C44 | C38: 1:24 | D38: 6648 | E38: =IF(D38="","",IF(D38<Параметры!$B$4,CEILING(D38*Параметры!$B$5,100)-10,IF(D38<=Параметры!$B$6,CEILING(D38*Параметры!$B$7,100)-10,CEILING(D38*Параметры!$B$8,100)-10))) -> 10690 | F38: =IF(D38="","",ROUND(E38*(1-Параметры!$B$9-Параметры!$B$10-Параметры!$B$11)-D38,0)) -> 2492 | G38: Kick Sauber C44 | H38: — | I38: CaDA | J38: 2024 | K38: 340 | L38: 4.7 | M38: открыть | N38: проверить | P38: =IF(COUNTIFS($G$5:$G$66,G38,$H$5:$H$66,H38,$I$5:$I$66,I38,$C$5:$C$66,C38)>1,"повтор","") | Q38: =IF(C38<>"1:24","",IF(D38="","проверить",IF(D38<=Параметры!$B$12,"ок","дороже лимита"))) -> дороже лимита | R38: Официальная лицензия Sauber. Цена — верхняя оценка (зачёркнутая цена), реальная может быть до двух раз ниже. Вариант «с коробкой» и его цену не проверяли: в CSV из Chrome этого лота нет.
A39: Конструкторы — реплика | B39: Red Bull RB21 — реплика 1:8 | C39: 1:8 | D39: 2849 | E39: =IF(D39="","",IF(D39<Параметры!$B$4,CEILING(D39*Параметры!$B$5,100)-10,IF(D39<=Параметры!$B$6,CEILING(D39*Параметры!$B$7,100)-10,CEILING(D39*Параметры!$B$8,100)-10))) -> 4590 | F39: =IF(D39="","",ROUND(E39*(1-Параметры!$B$9-Параметры!$B$10-Параметры!$B$11)-D39,0)) -> 1075 | G39: Red Bull RB21 | H39: — | I39: реплика | J39: 2025 | K39: 136 | L39: 4.9 | M39: открыть | N39: проверить | O39: 310056041 · 4699 ₽ | P39: =IF(COUNTIFS($G$5:$G$66,G39,$H$5:$H$66,H39,$I$5:$I$66,I39,$C$5:$C$66,C39)>1,"повтор","") | Q39: =IF(C39<>"1:24","",IF(D39="","проверить",IF(D39<=Параметры!$B$12,"ок","дороже лимита"))) | R39: Цена — верхняя оценка (зачёркнутая): в выдаче была только цена для новичков, реальная может быть до двух раз ниже. Вариант «с коробкой» и его цену не проверяли: в CSV из Chrome этого лота нет.
A40: Конструкторы — реплика | B40: Ferrari SF-25 — реплика 1:8 | C40: 1:8 | D40: 3044 | E40: =IF(D40="","",IF(D40<Параметры!$B$4,CEILING(D40*Параметры!$B$5,100)-10,IF(D40<=Параметры!$B$6,CEILING(D40*Параметры!$B$7,100)-10,CEILING(D40*Параметры!$B$8,100)-10))) -> 4890 | F40: =IF(D40="","",ROUND(E40*(1-Параметры!$B$9-Параметры!$B$10-Параметры!$B$11)-D40,0)) -> 1137 | G40: Ferrari SF-25 | H40: — | I40: реплика | J40: 2025 | K40: 75 | M40: открыть | N40: проверить | O40: 682211506 · 5967 ₽ | P40: =IF(COUNTIFS($G$5:$G$66,G40,$H$5:$H$66,H40,$I$5:$I$66,I40,$C$5:$C$66,C40)>1,"повтор","") | Q40: =IF(C40<>"1:24","",IF(D40="","проверить",IF(D40<=Параметры!$B$12,"ок","дороже лимита"))) | R40: Вариант «с коробкой» и его цену не проверяли: в CSV из Chrome этого лота нет.
A41: Конструкторы — реплика | B41: McLaren MCL39 — реплика 1:8 | C41: 1:8 | D41: 3563 | E41: =IF(D41="","",IF(D41<Параметры!$B$4,CEILING(D41*Параметры!$B$5,100)-10,IF(D41<=Параметры!$B$6,CEILING(D41*Параметры!$B$7,100)-10,CEILING(D41*Параметры!$B$8,100)-10))) -> 5790 | F41: =IF(D41="","",ROUND(E41*(1-Параметры!$B$9-Параметры!$B$10-Параметры!$B$11)-D41,0)) -> 1387 | G41: McLaren MCL39 | H41: — | I41: реплика | J41: 2025 | K41: 604 | L41: 4.9 | M41: открыть | N41: проверить | P41: =IF(COUNTIFS($G$5:$G$66,G41,$H$5:$H$66,H41,$I$5:$I$66,I41,$C$5:$C$66,C41)>1,"повтор","") | Q41: =IF(C41<>"1:24","",IF(D41="","проверить",IF(D41<=Параметры!$B$12,"ок","дороже лимита"))) | R41: Многовариантный лот: цена в выдаче — самого дешёвого варианта, MCL39 может стоить дороже. Вариант «с коробкой» и его цену не проверяли: в CSV из Chrome этого лота нет.
A42: Конструкторы — реплика | B42: Ferrari SF-24 — реплика 1:8 | C42: 1:8 | D42: 3563 | E42: =IF(D42="","",IF(D42<Параметры!$B$4,CEILING(D42*Параметры!$B$5,100)-10,IF(D42<=Параметры!$B$6,CEILING(D42*Параметры!$B$7,100)-10,CEILING(D42*Параметры!$B$8,100)-10))) -> 5790 | F42: =IF(D42="","",ROUND(E42*(1-Параметры!$B$9-Параметры!$B$10-Параметры!$B$11)-D42,0)) -> 1387 | G42: Ferrari SF-24 | H42: — | I42: реплика | J42: 2024 | K42: 604 | L42: 4.9 | M42: открыть | N42: проверить | O42: 748054401 · 4866 ₽ | P42: =IF(COUNTIFS($G$5:$G$66,G42,$H$5:$H$66,H42,$I$5:$I$66,I42,$C$5:$C$66,C42)>1,"повтор","") | Q42: =IF(C42<>"1:24","",IF(D42="","проверить",IF(D42<=Параметры!$B$12,"ок","дороже лимита"))) | R42: Вариант «с коробкой» и его цену не проверяли: в CSV из Chrome этого лота нет.
A43: Конструкторы — реплика | B43: Red Bull RB20 — реплика 1:8 | C43: 1:8 | D43: 3563 | E43: =IF(D43="","",IF(D43<Параметры!$B$4,CEILING(D43*Параметры!$B$5,100)-10,IF(D43<=Параметры!$B$6,CEILING(D43*Параметры!$B$7,100)-10,CEILING(D43*Параметры!$B$8,100)-10))) -> 5790 | F43: =IF(D43="","",ROUND(E43*(1-Параметры!$B$9-Параметры!$B$10-Параметры!$B$11)-D43,0)) -> 1387 | G43: Red Bull RB20 | H43: — | I43: реплика | J43: 2024 | K43: 604 | L43: 4.9 | M43: открыть | N43: проверить | O43: 748054401 · 4866 ₽ | P43: =IF(COUNTIFS($G$5:$G$66,G43,$H$5:$H$66,H43,$I$5:$I$66,I43,$C$5:$C$66,C43)>1,"повтор","") | Q43: =IF(C43<>"1:24","",IF(D43="","проверить",IF(D43<=Параметры!$B$12,"ок","дороже лимита"))) | R43: Вариант «с коробкой» и его цену не проверяли: в CSV из Chrome этого лота нет.
A44: Конструкторы — реплика | B44: Mercedes W14 — реплика 1:8 | C44: 1:8 | D44: 3854 | E44: =IF(D44="","",IF(D44<Параметры!$B$4,CEILING(D44*Параметры!$B$5,100)-10,IF(D44<=Параметры!$B$6,CEILING(D44*Параметры!$B$7,100)-10,CEILING(D44*Параметры!$B$8,100)-10))) -> 6190 | F44: =IF(D44="","",ROUND(E44*(1-Параметры!$B$9-Параметры!$B$10-Параметры!$B$11)-D44,0)) -> 1438 | G44: Mercedes W14 | H44: — | I44: реплика | J44: 2023 | K44: 148 | M44: открыть | N44: проверить | O44: 921806170 · 4383 ₽ | P44: =IF(COUNTIFS($G$5:$G$66,G44,$H$5:$H$66,H44,$I$5:$I$66,I44,$C$5:$C$66,C44)>1,"повтор","") | Q44: =IF(C44<>"1:24","",IF(D44="","проверить",IF(D44<=Параметры!$B$12,"ок","дороже лимита"))) | R44: Вариант «с коробкой» и его цену не проверяли: в CSV из Chrome этого лота нет.
A45: Конструкторы — реплика | B45: Aston Martin AMR25 — реплика 1:8 | C45: 1:8 | D45: 1904 | E45: =IF(D45="","",IF(D45<Параметры!$B$4,CEILING(D45*Параметры!$B$5,100)-10,IF(D45<=Параметры!$B$6,CEILING(D45*Параметры!$B$7,100)-10,CEILING(D45*Параметры!$B$8,100)-10))) -> 3090 | F45: =IF(D45="","",ROUND(E45*(1-Параметры!$B$9-Параметры!$B$10-Параметры!$B$11)-D45,0)) -> 738 | G45: Aston Martin AMR25 | H45: — | I45: реплика | J45: 2025 | K45: 138 | M45: открыть | N45: проверить | O45: 501309634 · 2853 ₽ | P45: =IF(COUNTIFS($G$5:$G$66,G45,$H$5:$H$66,H45,$I$5:$I$66,I45,$C$5:$C$66,C45)>1,"повтор","") | Q45: =IF(C45<>"1:24","",IF(D45="","проверить",IF(D45<=Параметры!$B$12,"ок","дороже лимита"))) | R45: Вариант «с коробкой» и его цену не проверяли: в CSV из Chrome этого лота нет.
A46: Постеры | B46: Постер McLaren M23 | C46: 30×40 см | D46: 629 | E46: =IF(D46="","",IF(D46<Параметры!$B$4,CEILING(D46*Параметры!$B$5,100)-10,IF(D46<=Параметры!$B$6,CEILING(D46*Параметры!$B$7,100)-10,CEILING(D46*Параметры!$B$8,100)-10))) -> 1290 | F46: =IF(D46="","",ROUND(E46*(1-Параметры!$B$9-Параметры!$B$10-Параметры!$B$11)-D46,0)) -> 474 | G46: McLaren M23 | H46: — | I46: — | J46: 1974 | K46: 112 | L46: 4.4 | M46: открыть | N46: SKU-1 / 30X40cm no frame | P46: =IF(COUNTIFS($G$5:$G$66,G46,$H$5:$H$66,H46,$I$5:$I$66,I46,$C$5:$C$66,C46)>1,"повтор","") | Q46: =IF(C46<>"1:24","",IF(D46="","проверить",IF(D46<=Параметры!$B$12,"ок","дороже лимита"))) | R46: Холст без рамки. Цены других размеров — лист «Постеры — размеры».
A47: Постеры | B47: Постер McLaren-Mercedes MP4-23 | C47: 30×40 см | D47: 629 | E47: =IF(D47="","",IF(D47<Параметры!$B$4,CEILING(D47*Параметры!$B$5,100)-10,IF(D47<=Параметры!$B$6,CEILING(D47*Параметры!$B$7,100)-10,CEILING(D47*Параметры!$B$8,100)-10))) -> 1290 | F47: =IF(D47="","",ROUND(E47*(1-Параметры!$B$9-Параметры!$B$10-Параметры!$B$11)-D47,0)) -> 474 | G47: McLaren-Mercedes MP4-23 | H47: — | I47: — | J47: 2008 | K47: 112 | L47: 4.4 | M47: открыть | N47: SKU-2 / 30X40cm no frame | P47: =IF(COUNTIFS($G$5:$G$66,G47,$H$5:$H$66,H47,$I$5:$I$66,I47,$C$5:$C$66,C47)>1,"повтор","") | Q47: =IF(C47<>"1:24","",IF(D47="","проверить",IF(D47<=Параметры!$B$12,"ок","дороже лимита"))) | R47: Холст без рамки. Цены других размеров — лист «Постеры — размеры».
A48: Постеры | B48: Постер McLaren MCL34 | C48: 30×40 см | D48: 629 | E48: =IF(D48="","",IF(D48<Параметры!$B$4,CEILING(D48*Параметры!$B$5,100)-10,IF(D48<=Параметры!$B$6,CEILING(D48*Параметры!$B$7,100)-10,CEILING(D48*Параметры!$B$8,100)-10))) -> 1290 | F48: =IF(D48="","",ROUND(E48*(1-Параметры!$B$9-Параметры!$B$10-Параметры!$B$11)-D48,0)) -> 474 | G48: McLaren MCL34 | H48: — | I48: — | J48: 2019 | K48: 112 | L48: 4.4 | M48: открыть | N48: SKU-3 / 30X40cm no frame | P48: =IF(COUNTIFS($G$5:$G$66,G48,$H$5:$H$66,H48,$I$5:$I$66,I48,$C$5:$C$66,C48)>1,"повтор","") | Q48: =IF(C48<>"1:24","",IF(D48="","проверить",IF(D48<=Параметры!$B$12,"ок","дороже лимита"))) | R48: Холст без рамки. Цены других размеров — лист «Постеры — размеры».
A49: Постеры | B49: Постер Lotus 98T | C49: 30×40 см | D49: 629 | E49: =IF(D49="","",IF(D49<Параметры!$B$4,CEILING(D49*Параметры!$B$5,100)-10,IF(D49<=Параметры!$B$6,CEILING(D49*Параметры!$B$7,100)-10,CEILING(D49*Параметры!$B$8,100)-10))) -> 1290 | F49: =IF(D49="","",ROUND(E49*(1-Параметры!$B$9-Параметры!$B$10-Параметры!$B$11)-D49,0)) -> 474 | G49: Lotus 98T | H49: — | I49: — | J49: 1986 | K49: 112 | L49: 4.4 | M49: открыть | N49: SKU-4 / 30X40cm no frame | P49: =IF(COUNTIFS($G$5:$G$66,G49,$H$5:$H$66,H49,$I$5:$I$66,I49,$C$5:$C$66,C49)>1,"повтор","") | Q49: =IF(C49<>"1:24","",IF(D49="","проверить",IF(D49<=Параметры!$B$12,"ок","дороже лимита"))) | R49: Холст без рамки. Цены других размеров — лист «Постеры — размеры».
A50: Постеры | B50: Постер Red Bull Racing RB16 | C50: 30×40 см | D50: 629 | E50: =IF(D50="","",IF(D50<Параметры!$B$4,CEILING(D50*Параметры!$B$5,100)-10,IF(D50<=Параметры!$B$6,CEILING(D50*Параметры!$B$7,100)-10,CEILING(D50*Параметры!$B$8,100)-10))) -> 1290 | F50: =IF(D50="","",ROUND(E50*(1-Параметры!$B$9-Параметры!$B$10-Параметры!$B$11)-D50,0)) -> 474 | G50: Red Bull Racing RB16 | H50: — | I50: — | J50: 2020 | K50: 112 | L50: 4.4 | M50: открыть | N50: SKU-5 / 30X40cm no frame | P50: =IF(COUNTIFS($G$5:$G$66,G50,$H$5:$H$66,H50,$I$5:$I$66,I50,$C$5:$C$66,C50)>1,"повтор","") | Q50: =IF(C50<>"1:24","",IF(D50="","проверить",IF(D50<=Параметры!$B$12,"ок","дороже лимита"))) | R50: Холст без рамки. Цены других размеров — лист «Постеры — размеры».
A51: Постеры | B51: Постер Lotus 99T | C51: 30×40 см | D51: 629 | E51: =IF(D51="","",IF(D51<Параметры!$B$4,CEILING(D51*Параметры!$B$5,100)-10,IF(D51<=Параметры!$B$6,CEILING(D51*Параметры!$B$7,100)-10,CEILING(D51*Параметры!$B$8,100)-10))) -> 1290 | F51: =IF(D51="","",ROUND(E51*(1-Параметры!$B$9-Параметры!$B$10-Параметры!$B$11)-D51,0)) -> 474 | G51: Lotus 99T | H51: — | I51: — | J51: 1987 | K51: 112 | L51: 4.4 | M51: открыть | N51: SKU-6 / 30X40cm no frame | P51: =IF(COUNTIFS($G$5:$G$66,G51,$H$5:$H$66,H51,$I$5:$I$66,I51,$C$5:$C$66,C51)>1,"повтор","") | Q51: =IF(C51<>"1:24","",IF(D51="","проверить",IF(D51<=Параметры!$B$12,"ок","дороже лимита"))) | R51: Холст без рамки. Цены других размеров — лист «Постеры — размеры».
A52: Постеры | B52: Постер Jordan 191 | C52: 30×40 см | D52: 629 | E52: =IF(D52="","",IF(D52<Параметры!$B$4,CEILING(D52*Параметры!$B$5,100)-10,IF(D52<=Параметры!$B$6,CEILING(D52*Параметры!$B$7,100)-10,CEILING(D52*Параметры!$B$8,100)-10))) -> 1290 | F52: =IF(D52="","",ROUND(E52*(1-Параметры!$B$9-Параметры!$B$10-Параметры!$B$11)-D52,0)) -> 474 | G52: Jordan 191 | H52: — | I52: — | J52: 1991 | K52: 112 | L52: 4.4 | M52: открыть | N52: SKU-7 / 30X40cm no frame | P52: =IF(COUNTIFS($G$5:$G$66,G52,$H$5:$H$66,H52,$I$5:$I$66,I52,$C$5:$C$66,C52)>1,"повтор","") | Q52: =IF(C52<>"1:24","",IF(D52="","проверить",IF(D52<=Параметры!$B$12,"ок","дороже лимита"))) | R52: Холст без рамки. Цены других размеров — лист «Постеры — размеры».
A53: Постеры | B53: Постер Mercedes AMG W10 | C53: 30×40 см | D53: 629 | E53: =IF(D53="","",IF(D53<Параметры!$B$4,CEILING(D53*Параметры!$B$5,100)-10,IF(D53<=Параметры!$B$6,CEILING(D53*Параметры!$B$7,100)-10,CEILING(D53*Параметры!$B$8,100)-10))) -> 1290 | F53: =IF(D53="","",ROUND(E53*(1-Параметры!$B$9-Параметры!$B$10-Параметры!$B$11)-D53,0)) -> 474 | G53: Mercedes AMG W10 | H53: — | I53: — | J53: 2019 | K53: 112 | L53: 4.4 | M53: открыть | N53: SKU-8 / 30X40cm no frame | P53: =IF(COUNTIFS($G$5:$G$66,G53,$H$5:$H$66,H53,$I$5:$I$66,I53,$C$5:$C$66,C53)>1,"повтор","") | Q53: =IF(C53<>"1:24","",IF(D53="","проверить",IF(D53<=Параметры!$B$12,"ок","дороже лимита"))) | R53: Холст без рамки. Цены других размеров — лист «Постеры — размеры».
A54: Постеры | B54: Постер McLaren MP4/5B | C54: 30×40 см | D54: 629 | E54: =IF(D54="","",IF(D54<Параметры!$B$4,CEILING(D54*Параметры!$B$5,100)-10,IF(D54<=Параметры!$B$6,CEILING(D54*Параметры!$B$7,100)-10,CEILING(D54*Параметры!$B$8,100)-10))) -> 1290 | F54: =IF(D54="","",ROUND(E54*(1-Параметры!$B$9-Параметры!$B$10-Параметры!$B$11)-D54,0)) -> 474 | G54: McLaren MP4/5B | H54: — | I54: — | J54: 1990 | K54: 112 | L54: 4.4 | M54: открыть | N54: SKU-9 / 30X40cm no frame | P54: =IF(COUNTIFS($G$5:$G$66,G54,$H$5:$H$66,H54,$I$5:$I$66,I54,$C$5:$C$66,C54)>1,"повтор","") | Q54: =IF(C54<>"1:24","",IF(D54="","проверить",IF(D54<=Параметры!$B$12,"ок","дороже лимита"))) | R54: Холст без рамки. Цены других размеров — лист «Постеры — размеры».
A55: Постеры | B55: Постер McLaren MP4/4 | C55: 30×40 см | D55: 629 | E55: =IF(D55="","",IF(D55<Параметры!$B$4,CEILING(D55*Параметры!$B$5,100)-10,IF(D55<=Параметры!$B$6,CEILING(D55*Параметры!$B$7,100)-10,CEILING(D55*Параметры!$B$8,100)-10))) -> 1290 | F55: =IF(D55="","",ROUND(E55*(1-Параметры!$B$9-Параметры!$B$10-Параметры!$B$11)-D55,0)) -> 474 | G55: McLaren MP4/4 | H55: — | I55: — | J55: 1988 | K55: 112 | L55: 4.4 | M55: открыть | N55: SKU-10 / 30X40cm no frame | P55: =IF(COUNTIFS($G$5:$G$66,G55,$H$5:$H$66,H55,$I$5:$I$66,I55,$C$5:$C$66,C55)>1,"повтор","") | Q55: =IF(C55<>"1:24","",IF(D55="","проверить",IF(D55<=Параметры!$B$12,"ок","дороже лимита"))) | R55: Холст без рамки. Цены других размеров — лист «Постеры — размеры».
A56: Постеры | B56: Постер McLaren MP4/6 | C56: 30×40 см | D56: 629 | E56: =IF(D56="","",IF(D56<Параметры!$B$4,CEILING(D56*Параметры!$B$5,100)-10,IF(D56<=Параметры!$B$6,CEILING(D56*Параметры!$B$7,100)-10,CEILING(D56*Параметры!$B$8,100)-10))) -> 1290 | F56: =IF(D56="","",ROUND(E56*(1-Параметры!$B$9-Параметры!$B$10-Параметры!$B$11)-D56,0)) -> 474 | G56: McLaren MP4/6 | H56: — | I56: — | J56: 1991 | K56: 112 | L56: 4.4 | M56: открыть | N56: SKU-11 / 30X40cm no frame | P56: =IF(COUNTIFS($G$5:$G$66,G56,$H$5:$H$66,H56,$I$5:$I$66,I56,$C$5:$C$66,C56)>1,"повтор","") | Q56: =IF(C56<>"1:24","",IF(D56="","проверить",IF(D56<=Параметры!$B$12,"ок","дороже лимита"))) | R56: Холст без рамки. Цены других размеров — лист «Постеры — размеры».
A57: Постеры | B57: Постер Brawn BGP001 | C57: 30×40 см | D57: 629 | E57: =IF(D57="","",IF(D57<Параметры!$B$4,CEILING(D57*Параметры!$B$5,100)-10,IF(D57<=Параметры!$B$6,CEILING(D57*Параметры!$B$7,100)-10,CEILING(D57*Параметры!$B$8,100)-10))) -> 1290 | F57: =IF(D57="","",ROUND(E57*(1-Параметры!$B$9-Параметры!$B$10-Параметры!$B$11)-D57,0)) -> 474 | G57: Brawn BGP001 | H57: — | I57: — | J57: 2009 | K57: 112 | L57: 4.4 | M57: открыть | N57: SKU-12 / 30X40cm no frame | P57: =IF(COUNTIFS($G$5:$G$66,G57,$H$5:$H$66,H57,$I$5:$I$66,I57,$C$5:$C$66,C57)>1,"повтор","") | Q57: =IF(C57<>"1:24","",IF(D57="","проверить",IF(D57<=Параметры!$B$12,"ок","дороже лимита"))) | R57: Холст без рамки. Цены других размеров — лист «Постеры — размеры».
... A65: Постеры | B65: Постер Red Bull Racing RB7 | C65: 30×40 см | D65: 629 | E65: =IF(D65="","",IF(D65<Параметры!$B$4,CEILING(D65*Параметры!$B$5,100)-10,IF(D65<=Параметры!$B$6,CEILING(D65*Параметры!$B$7,100)-10,CEILING(D65*Параметры!$B$8,100)-10))) -> 1290 | F65: =IF(D65="","",ROUND(E65*(1-Параметры!$B$9-Параметры!$B$10-Параметры!$B$11)-D65,0)) -> 474 | G65: Red Bull Racing RB7 | H65: — | I65: — | J65: 2011 | K65: 112 | L65: 4.4 | M65: открыть | N65: SKU-20 / 30X40cm no frame | P65: =IF(COUNTIFS($G$5:$G$66,G65,$H$5:$H$66,H65,$I$5:$I$66,I65,$C$5:$C$66,C65)>1,"повтор","") | Q65: =IF(C65<>"1:24","",IF(D65="","проверить",IF(D65<=Параметры!$B$12,"ок","дороже лимита"))) | R65: Холст без рамки. Цены других размеров — лист «Постеры — размеры».
A66: Постеры | B66: Постер Шумахер, Ferrari — японский стиль | C66: 30×40 см | D66: 629 | E66: =IF(D66="","",IF(D66<Параметры!$B$4,CEILING(D66*Параметры!$B$5,100)-10,IF(D66<=Параметры!$B$6,CEILING(D66*Параметры!$B$7,100)-10,CEILING(D66*Параметры!$B$8,100)-10))) -> 1290 | F66: =IF(D66="","",ROUND(E66*(1-Параметры!$B$9-Параметры!$B$10-Параметры!$B$11)-D66,0)) -> 474 | G66: Шумахер, Ferrari — японский стиль | H66: — | I66: — | K66: 112 | L66: 4.4 | M66: открыть | N66: SKU-21 / 30X40cm no frame | P66: =IF(COUNTIFS($G$5:$G$66,G66,$H$5:$H$66,H66,$I$5:$I$66,I66,$C$5:$C$66,C66)>1,"повтор","") | Q66: =IF(C66<>"1:24","",IF(D66="","проверить",IF(D66<=Параметры!$B$12,"ок","дороже лимита"))) | R66: Холст без рамки. Цены других размеров — лист «Постеры — размеры».
A68: Итого
A69: Позиций всего | B69: =COUNTA(B5:B66) -> 62
A70: Модели 1:43 — сезон 2025 | B70: =COUNTIF($A$5:$A$66,"Модели 1:43 — сезон 2025") -> 16
A71: Модели 1:43 — новинки 2026 | B71: =COUNTIF($A$5:$A$66,"Модели 1:43 — новинки 2026") -> 4
A72: Модели 1:24 | B72: =COUNTIF($A$5:$A$66,"Модели 1:24") -> 12
A73: Конструкторы — лицензия CaDA | B73: =COUNTIF($A$5:$A$66,"Конструкторы — лицензия CaDA") -> 2
A74: Конструкторы — реплика | B74: =COUNTIF($A$5:$A$66,"Конструкторы — реплика") -> 7
A75: Постеры | B75: =COUNTIF($A$5:$A$66,"Постеры") -> 21
A76: Повторов | B76: =COUNTIF(P5:P66,"повтор") -> 0
A77: 1:24 дороже лимита | B77: =COUNTIF(Q5:Q66,"дороже лимита") -> 2
A78: Средняя прибыль с шт., ₽ | B78: =IFERROR(ROUND(AVERAGE(F5:F66),0),"") -> 776
A79: Средняя прибыль, модели 1:43, ₽ | B79: =IFERROR(ROUND(AVERAGEIFS(F5:F66,C5:C66,"1:43"),0),"") -> 710
A80: Средняя прибыль, модели 1:24, ₽ | B80: =IFERROR(ROUND(AVERAGEIFS(F5:F66,C5:C66,"1:24",A5:A66,"Модели 1:24"),0),"") -> 934

Sheet Мерч и кепки
A1: TMFF — одежда в стиле командной формы
A2: Поиск aliexpress.com 25.09.2026. Цена пересчитана из $ по курсу с листа «Параметры»; жёлтая — верхняя оценка (в выдаче была только цена для новичков), реальная может быть до двух раз ниже. Прибыль — с резервом на возвраты по одежде (10 %).
A3: Только вещи в стиле официальной формы команд, на сайте — с пометкой «Реплика». Командные кепки и худи Ferrari, Red Bull, Mercedes и McLaren на aliexpress.com почти не показываются — стоит поискать их на aliexpress.ru. Номер № — на картинке merch-candidates.jpg.
A4: № | B4: Команда | C4: Название на сайте | D4: Вещь | E4: Команда | F4: Цена на Ali, ₽ | G4: Наша цена, ₽ | H4: Прибыль с шт., ₽ | I4: Заказов | J4: Рейтинг | K4: Лот | L4: Заметки и что проверить
A5: 1 | B5: Ferrari | C5: Футболка Ferrari · Хэмилтон 44 | D5: футболка | E5: Ferrari | F5: 792 | G5: =IF(F5="","",IF(F5<Параметры!$B$4,CEILING(F5*Параметры!$B$5,100)-10,IF(F5<=Параметры!$B$6,CEILING(F5*Параметры!$B$7,100)-10,CEILING(F5*Параметры!$B$8,100)-10))) -> 1590 | H5: =IF(F5="","",ROUND(G5*(1-Параметры!$B$9-Параметры!$B$10-Параметры!$B$14)-F5,0)) -> 488 | I5: 752 | J5: 4.5 | K5: открыть | L5: Стиль формы Ferrari 2026 с логотипами партнёров.
A6: 2 | B6: Ferrari | C6: Худи Ferrari · Хэмилтон 44 | D6: кофта | E6: Ferrari | F6: 3705 | G6: =IF(F6="","",IF(F6<Параметры!$B$4,CEILING(F6*Параметры!$B$5,100)-10,IF(F6<=Параметры!$B$6,CEILING(F6*Параметры!$B$7,100)-10,CEILING(F6*Параметры!$B$8,100)-10))) -> 5990 | H6: =IF(F6="","",ROUND(G6*(1-Параметры!$B$9-Параметры!$B$10-Параметры!$B$14)-F6,0)) -> 1117 | I6: 7 | K6: открыть | L6: Та же расцветка, что у футболки. Цена — верхняя оценка.
A7: 3 | B7: Ferrari | C7: Кепка Ferrari · Хэмилтон 44 | D7: кепка | E7: Ferrari | F7: 1909 | G7: =IF(F7="","",IF(F7<Параметры!$B$4,CEILING(F7*Параметры!$B$5,100)-10,IF(F7<=Параметры!$B$6,CEILING(F7*Параметры!$B$7,100)-10,CEILING(F7*Параметры!$B$8,100)-10))) -> 3090 | H7: =IF(F7="","",ROUND(G7*(1-Параметры!$B$9-Параметры!$B$10-Параметры!$B$14)-F7,0)) -> 578 | I7: 9 | K7: открыть | L7: Мало заказов — сначала образец. Цена — верхняя оценка.
A8: 4 | B8: McLaren | C8: Футболка McLaren · Норрис 4 | D8: футболка | E8: McLaren | F8: 773 | G8: =IF(F8="","",IF(F8<Параметры!$B$4,CEILING(F8*Параметры!$B$5,100)-10,IF(F8<=Параметры!$B$6,CEILING(F8*Параметры!$B$7,100)-10,CEILING(F8*Параметры!$B$8,100)-10))) -> 1590 | H8: =IF(F8="","",ROUND(G8*(1-Параметры!$B$9-Параметры!$B$10-Параметры!$B$14)-F8,0)) -> 507 | I8: 63 | J8: 4.8 | K8: открыть | L8: Форма McLaren 2025, номер 4.
A9: 5 | B9: McLaren | C9: Поло McLaren · Норрис 1 | D9: футболка | E9: McLaren | F9: 1342 | G9: =IF(F9="","",IF(F9<Параметры!$B$4,CEILING(F9*Параметры!$B$5,100)-10,IF(F9<=Параметры!$B$6,CEILING(F9*Параметры!$B$7,100)-10,CEILING(F9*Параметры!$B$8,100)-10))) -> 2690 | H9: =IF(F9="","",ROUND(G9*(1-Параметры!$B$9-Параметры!$B$10-Параметры!$B$14)-F9,0)) -> 823 | I9: 78 | J9: 4.1 | K9: открыть | L9: Командное поло 2026, номер 1.
A10: 6 | B10: McLaren | C10: Кепка McLaren · Норрис 4 | D10: кепка | E10: McLaren | F10: 670 | G10: =IF(F10="","",IF(F10<Параметры!$B$4,CEILING(F10*Параметры!$B$5,100)-10,IF(F10<=Параметры!$B$6,CEILING(F10*Параметры!$B$7,100)-10,CEILING(F10*Параметры!$B$8,100)-10))) -> 1390 | H10: =IF(F10="","",ROUND(G10*(1-Параметры!$B$9-Параметры!$B$10-Параметры!$B$14)-F10,0)) -> 449 | I10: 10 | K10: открыть | L10: Кепка в стиле кепки пилота; мало заказов. Цена — верхняя оценка.
A11: 7 | B11: Red Bull Racing | C11: Футболка Red Bull Racing · Ферстаппен 3 | D11: футболка | E11: Red Bull | F11: 1376 | G11: =IF(F11="","",IF(F11<Параметры!$B$4,CEILING(F11*Параметры!$B$5,100)-10,IF(F11<=Параметры!$B$6,CEILING(F11*Параметры!$B$7,100)-10,CEILING(F11*Параметры!$B$8,100)-10))) -> 2790 | H11: =IF(F11="","",ROUND(G11*(1-Параметры!$B$9-Параметры!$B$10-Параметры!$B$14)-F11,0)) -> 870 | I11: 22 | K11: открыть | L11: Форма Red Bull 2026, номер 3. Цена — верхняя оценка. Запасной: 3256812989321292.
A12: 8 | B12: Red Bull Racing | C12: Кепка Red Bull Racing · Ферстаппен 1 | D12: кепка | E12: Red Bull | F12: 1932 | G12: =IF(F12="","",IF(F12<Параметры!$B$4,CEILING(F12*Параметры!$B$5,100)-10,IF(F12<=Параметры!$B$6,CEILING(F12*Параметры!$B$7,100)-10,CEILING(F12*Параметры!$B$8,100)-10))) -> 3090 | H12: =IF(F12="","",ROUND(G12*(1-Параметры!$B$9-Параметры!$B$10-Параметры!$B$14)-F12,0)) -> 555 | I12: 4 | K12: открыть | L12: Кепка пилота с номером 1. Мало заказов — сначала образец. Цена — верхняя оценка.
A13: 9 | B13: Mercedes | C13: Футболка Mercedes · Рассел 63 | D13: футболка | E13: Mercedes | F13: 1661 | G13: =IF(F13="","",IF(F13<Параметры!$B$4,CEILING(F13*Параметры!$B$5,100)-10,IF(F13<=Параметры!$B$6,CEILING(F13*Параметры!$B$7,100)-10,CEILING(F13*Параметры!$B$8,100)-10))) -> 2690 | H13: =IF(F13="","",ROUND(G13*(1-Параметры!$B$9-Параметры!$B$10-Параметры!$B$14)-F13,0)) -> 504 | I13: 76 | K13: открыть | L13: Форма Mercedes 2026 с логотипами партнёров. Цена — верхняя оценка. Запасной: 3256811449048467.
A14: 10 | B14: Mercedes | C14: Флисовая кофта Mercedes | D14: кофта | E14: Mercedes | F14: 2656 | G14: =IF(F14="","",IF(F14<Параметры!$B$4,CEILING(F14*Параметры!$B$5,100)-10,IF(F14<=Параметры!$B$6,CEILING(F14*Параметры!$B$7,100)-10,CEILING(F14*Параметры!$B$8,100)-10))) -> 4290 | H14: =IF(F14="","",ROUND(G14*(1-Параметры!$B$9-Параметры!$B$10-Параметры!$B$14)-F14,0)) -> 797 | I14: 14 | K14: открыть | L14: Флиска на молнии с логотипом Petronas.
A15: 11 | B15: Aston Martin | C15: Кепка Aston Martin · Алонсо 14 | D15: кепка | E15: Aston Martin | F15: 986 | G15: =IF(F15="","",IF(F15<Параметры!$B$4,CEILING(F15*Параметры!$B$5,100)-10,IF(F15<=Параметры!$B$6,CEILING(F15*Параметры!$B$7,100)-10,CEILING(F15*Параметры!$B$8,100)-10))) -> 1990 | H15: =IF(F15="","",ROUND(G15*(1-Параметры!$B$9-Параметры!$B$10-Параметры!$B$14)-F15,0)) -> 616 | I15: 500 | J15: 4.8 | K15: открыть | L15: Самая продаваемая командная кепка в выдаче. Цена — верхняя оценка. Запасной: 3256810368072176.
A16: 12 | B16: Aston Martin | C16: Футболка Aston Martin · Алонсо 14 | D16: футболка | E16: Aston Martin | F16: 726 | G16: =IF(F16="","",IF(F16<Параметры!$B$4,CEILING(F16*Параметры!$B$5,100)-10,IF(F16<=Параметры!$B$6,CEILING(F16*Параметры!$B$7,100)-10,CEILING(F16*Параметры!$B$8,100)-10))) -> 1490 | H16: =IF(F16="","",ROUND(G16*(1-Параметры!$B$9-Параметры!$B$10-Параметры!$B$14)-F16,0)) -> 473 | I16: 194 | J16: 4.2 | K16: открыть | L16: Форма Aston Martin, номер 14.
A17: 13 | B17: Williams | C17: Футболка Williams · Сайнс 55 | D17: футболка | E17: Williams | F17: 738 | G17: =IF(F17="","",IF(F17<Параметры!$B$4,CEILING(F17*Параметры!$B$5,100)-10,IF(F17<=Параметры!$B$6,CEILING(F17*Параметры!$B$7,100)-10,CEILING(F17*Параметры!$B$8,100)-10))) -> 1490 | H17: =IF(F17="","",ROUND(G17*(1-Параметры!$B$9-Параметры!$B$10-Параметры!$B$14)-F17,0)) -> 461 | I17: 104 | J17: 4.3 | K17: открыть | L17: Форма Atlassian Williams 2026. Цена — верхняя оценка. Запасной: 3256809585305917.
A18: 14 | B18: Williams | C18: Поло Williams · Сайнс 55 | D18: футболка | E18: Williams | F18: 1119 | G18: =IF(F18="","",IF(F18<Параметры!$B$4,CEILING(F18*Параметры!$B$5,100)-10,IF(F18<=Параметры!$B$6,CEILING(F18*Параметры!$B$7,100)-10,CEILING(F18*Параметры!$B$8,100)-10))) -> 2290 | H18: =IF(F18="","",ROUND(G18*(1-Параметры!$B$9-Параметры!$B$10-Параметры!$B$14)-F18,0)) -> 724 | I18: 121 | J18: 4.1 | K18: открыть | L18: Командное поло 2026. Цена — верхняя оценка.
A19: 15 | B19: Williams | C19: Кепка Williams · Сайнс 55 | D19: кепка | E19: Williams | F19: 710 | G19: =IF(F19="","",IF(F19<Параметры!$B$4,CEILING(F19*Параметры!$B$5,100)-10,IF(F19<=Параметры!$B$6,CEILING(F19*Параметры!$B$7,100)-10,CEILING(F19*Параметры!$B$8,100)-10))) -> 1490 | H19: =IF(F19="","",ROUND(G19*(1-Параметры!$B$9-Параметры!$B$10-Параметры!$B$14)-F19,0)) -> 489 | I19: 88 | J19: 4.3 | K19: открыть | L19: Кепка пилота Карлоса Сайнса. Цена — верхняя оценка.
A20: 16 | B20: Audi | C20: Поло Audi | D20: футболка | E20: Audi | F20: 782 | G20: =IF(F20="","",IF(F20<Параметры!$B$4,CEILING(F20*Параметры!$B$5,100)-10,IF(F20<=Параметры!$B$6,CEILING(F20*Параметры!$B$7,100)-10,CEILING(F20*Параметры!$B$8,100)-10))) -> 1590 | H20: =IF(F20="","",ROUND(G20*(1-Параметры!$B$9-Параметры!$B$10-Параметры!$B$14)-F20,0)) -> 498 | I20: 131 | K20: открыть | L20: Поло Audi Sport, первый сезон Audi в Формуле 1.
A21: 17 | B21: Haas | C21: Худи Haas | D21: кофта | E21: Haas | F21: 1753 | G21: =IF(F21="","",IF(F21<Параметры!$B$4,CEILING(F21*Параметры!$B$5,100)-10,IF(F21<=Параметры!$B$6,CEILING(F21*Параметры!$B$7,100)-10,CEILING(F21*Параметры!$B$8,100)-10))) -> 2890 | H21: =IF(F21="","",ROUND(G21*(1-Параметры!$B$9-Параметры!$B$10-Параметры!$B$14)-F21,0)) -> 573 | I21: 4 | K21: открыть | L21: Худи с логотипом Haas. Мало заказов — сначала образец.
A22: 18 | B22: Ferrari | C22: Футболка Ferrari · Леклер 16 | D22: футболка | E22: Ferrari | F22: 1331 | G22: =IF(F22="","",IF(F22<Параметры!$B$4,CEILING(F22*Параметры!$B$5,100)-10,IF(F22<=Параметры!$B$6,CEILING(F22*Параметры!$B$7,100)-10,CEILING(F22*Параметры!$B$8,100)-10))) -> 2690 | H22: =IF(F22="","",ROUND(G22*(1-Параметры!$B$9-Параметры!$B$10-Параметры!$B$14)-F22,0)) -> 834 | I22: 32 | K22: открыть | L22: Та же форма Ferrari 2026, вариант Леклера. Цена — верхняя оценка.
A23: 19 | B23: Ferrari | C23: Футболка Ferrari | D23: футболка | E23: Ferrari | F23: 2027 | G23: =IF(F23="","",IF(F23<Параметры!$B$4,CEILING(F23*Параметры!$B$5,100)-10,IF(F23<=Параметры!$B$6,CEILING(F23*Параметры!$B$7,100)-10,CEILING(F23*Параметры!$B$8,100)-10))) -> 3290 | H23: =IF(F23="","",ROUND(G23*(1-Параметры!$B$9-Параметры!$B$10-Параметры!$B$14)-F23,0)) -> 621 | I23: 11 | K23: открыть | L23: Командная футболка без номера пилота. Цена — верхняя оценка.
A24: 20 | B24: Ferrari | C24: Футболка Ferrari «Монца» | D24: футболка | E24: Ferrari | F24: 2027 | G24: =IF(F24="","",IF(F24<Параметры!$B$4,CEILING(F24*Параметры!$B$5,100)-10,IF(F24<=Параметры!$B$6,CEILING(F24*Параметры!$B$7,100)-10,CEILING(F24*Параметры!$B$8,100)-10))) -> 3290 | H24: =IF(F24="","",ROUND(G24*(1-Параметры!$B$9-Параметры!$B$10-Параметры!$B$14)-F24,0)) -> 621 | I24: 9 | K24: открыть | L24: Спецвыпуск к Гран-при Италии, синяя. Год уточнить по фото. Цена — верхняя оценка.
A25: 21 | B25: Ferrari | C25: Кепка Ferrari «Монца» | D25: кепка | E25: Ferrari | F25: 1927 | G25: =IF(F25="","",IF(F25<Параметры!$B$4,CEILING(F25*Параметры!$B$5,100)-10,IF(F25<=Параметры!$B$6,CEILING(F25*Параметры!$B$7,100)-10,CEILING(F25*Параметры!$B$8,100)-10))) -> 3090 | H25: =IF(F25="","",ROUND(G25*(1-Параметры!$B$9-Параметры!$B$10-Параметры!$B$14)-F25,0)) -> 560 | I25: 4 | K25: открыть | L25: Синяя кепка спецвыпуска к Гран-при Италии. Мало заказов. Цена — верхняя оценка.
A26: 22 | B26: Red Bull Racing | C26: Лонгслив Red Bull Racing · Перес 11 | D26: футболка | E26: Red Bull | F26: 1820 | G26: =IF(F26="","",IF(F26<Параметры!$B$4,CEILING(F26*Параметры!$B$5,100)-10,IF(F26<=Параметры!$B$6,CEILING(F26*Параметры!$B$7,100)-10,CEILING(F26*Параметры!$B$8,100)-10))) -> 2990 | H26: =IF(F26="","",ROUND(G26*(1-Параметры!$B$9-Параметры!$B$10-Параметры!$B$14)-F26,0)) -> 587 | I26: 42 | K26: открыть | L26: Форма Red Bull с длинным рукавом, номер Переса — сезоны 2021–2024. Цена — верхняя оценка.
A27: 23 | B27: Red Bull Racing | C27: Кепка Red Bull Racing · Перес 11 | D27: кепка | E27: Red Bull | F27: 588 | G27: =IF(F27="","",IF(F27<Параметры!$B$4,CEILING(F27*Параметры!$B$5,100)-10,IF(F27<=Параметры!$B$6,CEILING(F27*Параметры!$B$7,100)-10,CEILING(F27*Параметры!$B$8,100)-10))) -> 1190 | H27: =IF(F27="","",ROUND(G27*(1-Параметры!$B$9-Параметры!$B$10-Параметры!$B$14)-F27,0)) -> 370 | I27: 33 | K27: открыть | L27: Кепка пилота Серхио Переса. Цена — верхняя оценка.
A28: 24 | B28: Mercedes | C28: Футболка Mercedes · Антонелли 12 | D28: футболка | E28: Mercedes | F28: 1083 | G28: =IF(F28="","",IF(F28<Параметры!$B$4,CEILING(F28*Параметры!$B$5,100)-10,IF(F28<=Параметры!$B$6,CEILING(F28*Параметры!$B$7,100)-10,CEILING(F28*Параметры!$B$8,100)-10))) -> 2190 | H28: =IF(F28="","",ROUND(G28*(1-Параметры!$B$9-Параметры!$B$10-Параметры!$B$14)-F28,0)) -> 680 | I28: 96 | J28: 4.4 | K28: открыть | L28: Форма Mercedes 2026, номер Антонелли.
A29: 25 | B29: Mercedes | C29: Кепка Mercedes · Хэмилтон 44 | D29: кепка | E29: Mercedes | F29: 301 | G29: =IF(F29="","",IF(F29<Параметры!$B$4,CEILING(F29*Параметры!$B$5,100)-10,IF(F29<=Параметры!$B$6,CEILING(F29*Параметры!$B$7,100)-10,CEILING(F29*Параметры!$B$8,100)-10))) -> 690 | H29: =IF(F29="","",ROUND(G29*(1-Параметры!$B$9-Параметры!$B$10-Параметры!$B$14)-F29,0)) -> 254 | I29: 6 | K29: открыть | L29: Кепка с номером 44 в стиле эпохи Хэмилтона в Mercedes.
A31: Итого
B32: Позиций | C32: =COUNTA(C5:C29) -> 25
B33: футболка | C33: =COUNTIF($D$5:$D$29,"футболка") -> 14
B34: кофта | C34: =COUNTIF($D$5:$D$29,"кофта") -> 3
B35: кепка | C35: =COUNTIF($D$5:$D$29,"кепка") -> 8
B36: Средняя прибыль, ₽ | C36: =IFERROR(ROUND(AVERAGE($H$5:$H$29),0),"") -> 602

Sheet Мерч — все лоты
A1: Все найденные лоты одежды и кепок — 739
A2: Тип, команда и риск определены по названию лота автоматически — могут быть ошибки. Отсортировано по заказам. Фильтр в заголовке — чтобы смотреть по вещи, команде или риску.
A4: Вещь | B4: Команда | C4: Риск по названию | D4: Название лота | E4: Цена, ₽ | F4: Для новичков, $ | G4: Заказов | H4: Рейтинг | I4: Лот | J4: Запрос
A5: кепка | B5: Легенды | C5: имя/образ пилота | D5: New Ayrton Senna Racer Fashion Embroidery Cap Outdoor Sun Protection Team Baseball Cap | E5: 1087 | F5: 1.09 | G5: 10000 | H5: 4.7 | I5: открыть | J5: f1 cap
A6: футболка | B6: — | C6: своя печать | D6: Custom Cotton Customized Print Short Sleeve T Shirt Summer Tops Tees DIY Your Like Photo Or Logo Cotton T-shirt Men Clothing | E6: 1156 | F6: 1.28 | G6: 10000 | H6: 4.6 | I6: открыть | J6: custom print t shirt heavyweight cotton
A7: футболка | B7: — | C7: своя печать | D7: Men's Cotton T-shirt Personalized Your Design Here Custom Text Tshirt for Men Add Your Own Design Fashion T Shirt Men Clothing | E7: 1005 | G7: 5000 | H7: 4.7 | I7: открыть | J7: ferrari f1 t shirt
A8: футболка | B8: — | C8: своя печать | D8: Men's Personalized Cotton T-shirt Custom Text Name Tsihrts Add Your Own Message Fashion men tshirt bigger size 4XL 5XL | E8: 994 | G8: 5000 | H8: 4.7 | I8: открыть | J8: ferrari f1 t shirt
A9: футболка | B9: — | C9: своя печать | D9: Custom T-shirt Customized Print T Shirt Men Women Personalized Tops Tees DIY Your Like Photo Or Logo Cotton T-shirt Men Clothing | E9: 1201 | F9: 1.13 | G9: 5000 | H9: 4.7 | I9: открыть | J9: red bull racing t shirt
A10: футболка | B10: — | C10: своя печать | D10: 180g Custom Women Men Customised Printed 100% Cotton Short Sleeve Your Logo Photo Brand Text Tee Personalize Graphic Clothing | E10: 789 | F10: 3.37 | G10: 5000 | H10: 4.9 | I10: открыть | J10: custom print t shirt heavyweight cotton
A11: футболка | B11: — | C11: своя печать | D11: 100% Cotton T-shirt Custom Logo Street Trend Short Sleeve T-shirt Embroidery Design European American Size Tops Printing Pattern | E11: 1449 | G11: 5000 | H11: 4.8 | I11: открыть | J11: custom print t shirt heavyweight cotton
A12: кофта | B12: — | C12: своя печать | D12: DIY Custom Your Brand LOGO Men Women Casual Hoodie Top Solid Color Pullover Street Personality Sweatshirt Custom Gifts | E12: 2593 | F12: 8.16 | G12: 5000 | H12: 4.8 | I12: открыть | J12: custom logo hoodie heavyweight
A13: футболка | B13: — | C13: своя печать | D13: Custom T Shirt Make Your Design Logo Text Front And Back T-shirt Men Print Cotton Tshirt Personalized Gift Customized Tees Tops | E13: 1186 | F13: 0.99 | G13: 4000 | H13: 4.7 | I13: открыть | J13: ferrari f1 t shirt
A14: поло | B14: — | C14: своя печать | D14: Customized Logo Breathable Polo Shirt Casual Company Group Clothing Lapel Short Sleeve Polo Shirts Work Clothes Print Embroidery | E14: 1778 | F14: 0.99 | G14: 4000 | H14: 4.3 | I14: открыть | J14: ferrari f1 t shirt
A15: футболка | B15: — | C15: своя печать | D15: Custom-Made Men's T-Shirts Are Suitable for Team Gatherings, Gyms, and Sports Cotton Round-Neck Short-Sleeved Shirts | E15: 1818 | F15: 4.15 | G15: 4000 | H15: 4.6 | I15: открыть | J15: red bull racing t shirt
A16: футболка | B16: — | C16: своя печать | D16: Customized Print T Shirt Men Women Custom Cotton Tops Tees DIY Your Like Photo Or Logo Cotton T-shirt Personalized Men Clothing | E16: 485 | G16: 4000 | H16: 4.6 | I16: открыть | J16: custom print t shirt heavyweight cotton
A17: футболка | B17: — | C17: своя печать | D17: Customized Printed Leisure T Shirt Tee DIY Your Own Design Like Photo Or Logo White T-shirt Fashion Custom Men's Tops Tshirt | E17: 1265 | G17: 4000 | H17: 4.9 | I17: открыть | J17: custom print t shirt heavyweight cotton
A18: футболка | B18: — | C18: своя печать | D18: Custom Unisex Tshirt Add Your Own Message Cotton O Neck Top Tees Bigger Size Gift Custom Unisex Personalized Tshirts 4XL 5XL | E18: 771 | G18: 4000 | H18: 4.7 | I18: открыть | J18: custom print t shirt heavyweight cotton
A19: кепка | B19: — | C19: своя печать | D19: SLECKTON Custom Baseball Cap Fashion DIY Letter Embroidery Hats for Women and Men Cotton Design LOGO Wholesale Unisex Caps | E19: 1087 | F19: 1.23 | G19: 3000 | H19: 4.8 | I19: открыть | J19: ferrari f1 cap
A20: футболка | B20: — | C20: своя печать | D20: Add Your Own Custom Text Name Personalized Message Men's T Shirt Casual Dress High Quality MensT-shirt5xL | E20: 549 | G20: 3000 | H20: 4.8 | I20: открыть | J20: ferrari f1 t shirt
A21: футболка | B21: — | C21: своя печать | D21: New Custom Compression T Shirt Your Design Logo Top Men Women Print Original Design Tshirts Jogging Workout Gym Quick Dry Tshirt | E21: 848 | F21: 0.99 | G21: 3000 | H21: 4.8 | I21: открыть | J21: ferrari f1 t shirt
A22: поло | B22: — | C22: своя печать | D22: Summer Casual Cheap POLO Shirt Personal Company Logo Customization Embroidery Printing Personalized Design Top | E22: 851 | F22: 2.29 | G22: 3000 | H22: 4.7 | I22: открыть | J22: red bull racing t shirt
A23: кепка | B23: — | C23: своя печать | D23: 1 Piece Summer Trucker Hat Custom Logo Men Women Net Polyester Baseball Cap Print Mesh Dad Hats Adjustable Sun Hat Visor | E23: 765 | F23: 1.09 | G23: 2000 | H23: 4.6 | I23: открыть | J23: ferrari f1 cap
A24: кепка | B24: — | C24: своя печать | D24: SLECKTON Custom Logo High-quality Suede Mesh Baseball Hat Letter Embroidery Brand Design Outdoor Sport Cap Wholesale Fashion | E24: 1364 | F24: 1.94 | G24: 2000 | H24: 4.7 | I24: открыть | J24: custom logo embroidery baseball cap
A25: футболка | B25: — | C25: своя печать | D25: Your Design Here T Shirts Cotton Custom T-Shirt Make Your Design Logo Text for Men and Women Personalized Tshirt Summer Presents | E25: 1070 | G25: 2000 | H25: 4.8 | I25: открыть | J25: ferrari f1 t shirt
A26: футболка | B26: — | C26: своя печать | D26: UE Size Custom Team T-shirt for Women, Add Your Own Design in Front and Back, Print and Text, High-quality T-shirt for Men | E26: 723 | F26: 0.99 | G26: 2000 | H26: 4.6 | I26: открыть | J26: ferrari f1 t shirt
A27: футболка | B27: — | C27: своя печать | D27: 3d Printing Custom T-shirts Summer Plus Size T-shirt Design E-sports Jersey Customization Sports Outdoor Cool Round Neck Tops | E27: 584 | G27: 2000 | I27: открыть | J27: ferrari f1 t shirt
A28: кофта | B28: — | C28: своя печать | D28: Personalized DIY Fashion T-Shirts Polyester Fabric Comfortable Breathable Sweatshirts High Quality Unisex Customized Tops | E28: 614 | G28: 2000 | H28: 4.9 | I28: открыть | J28: ferrari f1 t shirt
A29: футболка | B29: — | C29: своя печать | D29: Custom Your Exclusive 3D All Over Print T Shirt For Men Fashion Hip Hop Short Sleeve Tops Men Women Kids DIY Wholesale T-shirts | E29: 467 | F29: 1.09 | G29: 2000 | H29: 4.9 | I29: открыть | J29: mclaren f1 t shirt
A30: кепка | B30: — | C30: своя печать | D30: Custom Text Logo Embroidery Vintage Washed Cotton Baseball Cap Fashion Women Men Hat Sport Visors Snapback Cap Sun Hat | E30: 585 | G30: 2000 | H30: 4.7 | I30: открыть | J30: custom logo embroidery baseball cap
A31: кепка | B31: — | C31: своя печать | D31: SLECKTON Custom Cap Logo Embroidery Retro Baseball Cap for Men and Women DIY Design Letter Hat Customize Graphic Print Wholesale | E31: 573 | G31: 2000 | H31: 4.8 | I31: открыть | J31: custom logo embroidery baseball cap
A32: кепка | B32: — | C32: своя печать | D32: Custom Embroidered Baseball Caps For Men Woman Hat Custom Logo Men's Cap Snapback Embroidery Print Text Design Trucker Mesh Hats | E32: 377 | G32: 2000 | H32: 4.8 | I32: открыть | J32: custom logo embroidery baseball cap
A33: футболка | B33: — | C33: своя печать | D33: Personalized Custom Print Summer Y2K Team T-Shirt Cotton Casual Loose Short Sleeve Basics Fashion Tee Work Breathable Streetwear | E33: 1548 | F33: 2.46 | G33: 2000 | H33: 4.7 | I33: открыть | J33: custom print t shirt heavyweight cotton
A34: футболка | B34: — | C34: своя печать | D34: Men's Custom T-shirt With Your Own Logo Text And Photo Printed On The Front And Back Tshirt Costume Graphic Tee Tops | E34: 578 | G34: 2000 | H34: 4.7 | I34: открыть | J34: custom print t shirt heavyweight cotton
A35: футболка | B35: — | C35: своя печать | D35: Customized T-Shirts Free Printing Logo Images Old Design Clothes 100% Cotton Cultural Shirts Men's and Women's Work Clothes | E35: 1975 | F35: 3.39 | G35: 2000 | H35: 4.8 | I35: открыть | J35: custom print t shirt heavyweight cotton
A36: кофта | B36: — | C36: своя печать | D36: Customized 60% Cotton Hoodie Men Fashion Long Sleeve Sweatshirts Women Personality Printed Streetwear Hoody Pullovers Sudaderas | E36: 1340 | G36: 2000 | H36: 4.6 | I36: открыть | J36: custom logo hoodie heavyweight
A37: кепка | B37: — | C37: своя печать | D37: Custom Logo Diy Baseball Cap Unisex Adjustable Men Women Sport Trucker Hat Solid Color Personalized Print Hip Hop Dad Caps | E37: 401 | F37: 1.09 | G37: 1000 | H37: 4.5 | I37: открыть | J37: ferrari f1 cap
A38: кепка | B38: — | C38: своя печать | D38: Multi Colors Foam Trucker Caps Custom Logo Sports Hip Hop Snapback Hats Men Women Breathable Baseball Cap Diy Personalised Logo | E38: 283 | G38: 1000 | H38: 4.8 | I38: открыть | J38: ferrari f1 cap
A39: кепка | B39: — | C39: своя печать | D39: Unisex Summer Cheaper Trucker Hat Custom Logo Personality Baseball Cap Breathable Mesh Casual Snapback Hat Visor | E39: 407 | G39: 1000 | H39: 4.6 | I39: открыть | J39: ferrari f1 cap
A40: кепка | B40: — | C40: своя печать | D40: Customize Men Caps Custom Baseball Cap Women Tennis Hats Print Or Embroidery Logo Text Casual Hats Black Cap Visors Hats | E40: 528 | G40: 1000 | H40: 4.7 | I40: открыть | J40: ferrari f1 cap
A41: кепка | B41: — | C41: своя печать | D41: Custom Baseball Caps Hat Custom Logo Men's Cap Hip Hop Snapback Adjustable Embroidery Print DIY Team Logo Designer Baseball Caps | E41: 308 | G41: 1000 | H41: 4.9 | I41: открыть | J41: mclaren f1 cap
A42: кепка | B42: Aston Martin | C42: логотип команды | D42: 2025 Aston Martin Team Baseball Cap for Men Women Unisex Adjustable For Snapback Hat Sporty Design Trendy Accessories | E42: 915 | F42: 1.01 | G42: 1000 | H42: 4.4 | I42: открыть | J42: mclaren f1 cap
A43: поло | B43: — | C43: нет F1 в названии | D43: AIOPESON Embroidery 35% Cotton Polo Shirts for Men Casual Solid Color Slim Fit Mens Polos New Summer Fashion Brand Men Clothing | E43: 750 | F43: 0.99 | G43: 1000 | H43: 4.7 | I43: открыть | J43: mclaren f1 cap
A44: кепка | B44: — | C44: своя печать | D44: Custom Logo Hat Unisex Baseball Cap Men Women Snapback Hat Casual Solid Color Hip Hop Dad Caps Adult Sports Hat gorras hombre | E44: 317 | G44: 1000 | H44: 4.8 | I44: открыть | J44: aston martin f1 cap
A45: футболка | B45: — | C45: нет F1 в названии | D45: Summer Fox Racing Cross - country Mountain Bike Commemorative T - shirt High Quality Fashion Men Women Short Sleeve Round Neck | E45: 1429 | F45: 1.09 | G45: 1000 | H45: 4.2 | I45: открыть | J45: f1 t shirt
A46: футболка | B46: — | C46: своя печать | D46: Custom Design T Shirt Your Own Logo Men Casual Tees Cotton Short Sleeve Cool Tops Customized Tshirt | E46: 813 | G46: 1000 | I46: открыть | J46: ferrari f1 t shirt
A47: футболка | B47: — | C47: своя печать | D47: Customized Cotton Printed T-shirts Men Fashion Your Logo Tshirt Women Personality Casual Streetwear Custom Tee Tops | E47: 610 | G47: 1000 | H47: 4.8 | I47: открыть | J47: ferrari f1 t shirt
A48: футболка | B48: — | C48: своя печать | D48: Customized Your Design Here T Shit Text Name Tsihrt Add Your Own Message Men's T-shirt Personalized Tees Custom Cotton Tshirt | E48: 962 | G48: 1000 | H48: 4.8 | I48: открыть | J48: ferrari f1 t shirt
A49: футболка | B49: — | C49: своя печать | D49: Personalized DIY Custom T-shirt Jersey Polyester Fiber Material Round Neck Tops Printing High Quality Short Sleeve Tees Purchase | E49: 507 | G49: 1000 | H49: 4.8 | I49: открыть | J49: ferrari f1 t shirt
A50: футболка | B50: — | C50: своя печать | D50: EU size 100% pure cotton custom T-shirt front and back team school uniform store logo text photo for men's personalized high-end | E50: 992 | F50: 1.92 | G50: 1000 | H50: 4.8 | I50: открыть | J50: ferrari f1 t shirt
A51: поло | B51: — | C51: своя печать | D51: Summer Casual Breathable Polo Shirts Company Logo Custom Print Embroidery Personalized Design Men And Women Short-Sleeved Tops | E51: 372 | G51: 1000 | H51: 4.3 | I51: открыть | J51: ferrari f1 t shirt
A52: футболка | B52: — | C52: своя печать | D52: Men's Custom T-shirt With Your Own Logo Tshirt Text And Photo Printed On The Front And Back T Shirt Custom Gift Tees Clothing | E52: 548 | G52: 1000 | H52: 4.8 | I52: открыть | J52: red bull racing t shirt
A53: футболка | B53: — | C53: своя печать | D53: Tailor-made Custom Text Name Tsihrts Add Your Own Message Men's Cotton T-shirt Personalized Tee Your Design Men's Tshirt | E53: 704 | G53: 1000 | H53: 4.7 | I53: открыть | J53: mclaren f1 t shirt
A54: кепка | B54: — | C54: своя печать | D54: SLECKTON Custom Baseball Cap Fashion Letter Embroidery Sun Hats for Women and Men Cotton Design LOGO Wholesale Unisex Caps | E54: 911 | G54: 1000 | H54: 4.9 | I54: открыть | J54: custom logo embroidery baseball cap
A55: кепка | B55: — | C55: своя печать | D55: SLECKTON Custom Baseball Cap for Women and Men Fashion Design Brand LOGO Letter Embroidery Hats Corduroy Hats Unisex Wholesale | E55: 584 | G55: 1000 | H55: 4.8 | I55: открыть | J55: custom logo embroidery baseball cap
A56: футболка | B56: — | C56: своя печать | D56: Custom T shirt Women Men Customised Printed 100% Cotton Short Sleeve Your Logo Photo Brand Text Tee Personalize Graphic Clothing | E56: 927 | F56: 5.01 | G56: 1000 | H56: 4.8 | I56: открыть | J56: custom print t shirt heavyweight cotton
A57: футболка | B57: — | C57: своя печать | D57: Men's Personalized T-shirt 100%Cotton Tee Custom Shirt Make Your Design Logo Text Men Women Design Your Gift Couple Tshirt | E57: 1903 | F57: 4.62 | G57: 1000 | H57: 4.7 | I57: открыть | J57: custom print t shirt heavyweight cotton
A58: футболка | B58: — | C58: своя печать | D58: 6.7oz 190gsm Combed Cotton Tees Tshirts Mens Solid Tops Woman Male Custom Team Uniform Class Clothes Summer Brand Customization | E58: 742 | G58: 1000 | H58: 4.9 | I58: открыть | J58: custom print t shirt heavyweight cotton
A59: футболка | B59: — | C59: своя печать | D59: Custom T-shirt with Hip-hop Street Team Logo Men's 230G Pure Cotton, Loose Fit, High-temperature Printed Custom Top | E59: 1065 | F59: 6.65 | G59: 1000 | H59: 4.8 | I59: открыть | J59: custom print t shirt heavyweight cotton
A60: футболка | B60: — | C60: нет F1 в названии | D60: Desktop_Amazing Tees Men Ohlins Shock Suspension Car Motorcycle Sport Racing T Shirt Summer Casual Oversized men's Short sleeve | E60: 1859 | F60: 3.24 | G60: 1000 | H60: 4.5 | I60: открыть | J60: f1 racing car graphic t shirt
A61: кепка | B61: — | C61: своя печать | D61: Custom Baseball Caps Adjustable Embroidery Print Hat Custom Logo Men's Cap Hip Hop Snapback DIY Team Logo Designer Baseball Caps Adjustable fit for all head sizes 951 sold 4.8 | E61: 466 | G61: 951 | I61: открыть | J61: red bull racing cap
A62: кепка | B62: — | C62: своя печать | D62: Custom Logo Kids Adult Foam Trucker Hat Summer Adjustable Dad Hat Popular Sports Cap Boy Girls Mesh Caps School Activity Gorras Boys and youth 844 sold 4.8 | E62: 276 | G62: 844 | I62: открыть | J62: red bull racing cap
A63: кепка | B63: — | C63: своя печать | D63: SLECKTON Custom Logo Hats High-quality Hiphop Snapback Caps Letter Embroidery Brand Design Trucker Cap Wholesale Hat Adult | E63: 722 | G63: 800 | H63: 4.4 | I63: открыть | J63: ferrari f1 cap
A64: футболка | B64: — | C64: своя печать | D64: Custom T Shirt Make Your Design Logo Text Men Print Company Team Cotton Tshirt Personalized T-shirt Gift Tees Tops | E64: 724 | G64: 800 | H64: 4.5 | I64: открыть | J64: red bull racing t shirt
A65: кепка | B65: — | C65: своя печать | D65: Personalized Logo Design Baseball Caps Custom Logo Sorority Cap Embroidery Monogram Color Block Baseball Caps Hip Hop Hats | E65: 562 | G65: 800 | H65: 4.7 | I65: открыть | J65: custom logo embroidery baseball cap
A66: кофта | B66: — | C66: своя печать | D66: Customize Your Own Design Hoodie Personalized Embroidery Photo Logo Sweatshirt for Men and Women Casual Company Group Clothing | E66: 882 | F66: 4.48 | G66: 800 | I66: открыть | J66: custom logo hoodie heavyweight
A67: кепка | B67: — | C67: нет F1 в названии | D67: Funny Adventure Dad Hat Snapback Hat Bamboo Dragonfly Rainbow Sun Cap Helicopter Propeller Design for Kids Boys Girls Adult | E67: 389 | F67: 0.99 | G67: 700 | H67: 4.6 | I67: открыть | J67: mclaren f1 cap
A68: футболка | B68: Ferrari | C68: логотип команды | D68: 2026 New Special Edition Hamilton Summer Unisex Motorsport Fans 44 Red Black Racing Team Uniform Jersey T-Shirt | E68: 792 | G68: 700 | H68: 4.5 | I68: открыть | J68: ferrari f1 t shirt
A69: футболка | B69: — | C69: своя печать | D69: Customized Printed T Shirt Summer Gifts Tops Design Your Own Photo Or Logo T-shirt Custom Men's Tees Personalized Gift Tshirt | E69: 781 | G69: 700 | H69: 4.8 | I69: открыть | J69: custom print t shirt heavyweight cotton
A70: кепка | B70: — | C70: своя печать | D70: Custom Embroidery Trucker Hat for Men and Women DIY Design Baseball cap LOGO Print Hat Quality Truck Hat Wholesale Unisex Reflects fashion 696 sold 4.5 | E70: 92 | G70: 696 | I70: открыть | J70: red bull racing cap
A71: кепка | B71: — | C71: своя печать | D71: Custom Brand Diy Logo Baseball Cap For Men And Women Plain Blank Embroidery Print 5 Panel Sport Hat Basic Gorras Stays strong through seasons 612 sold 4.2 | E71: 92 | G71: 612 | I71: открыть | J71: red bull racing cap
A72: футболка | B72: — | C72: нет F1 в названии | D72: Men's Summer T-shirt with Top-level Racing Element Pattern Print 100% Cotton Breathable Round Neck Trendy Street Style Fashion | E72: 925 | G72: 600 | H72: 4.6 | I72: открыть | J72: f1 t shirt
A73: футболка | B73: — | C73: своя печать | D73: New DIY Pattern T-Shirt For Men Women Personalized Custom 3D Printed T Shirts Summer Casual Short Sleeve O-Neck Tops Street Tees | E73: 173 | G73: 600 | H73: 4.9 | I73: открыть | J73: ferrari f1 t shirt
A74: поло | B74: — | C74: своя печать | D74: Summer Quick Drying POLO Shirt Logo Custom Printing Embroidery Golf Custom Your Logo Sports T-shirt Top | E74: 880 | G74: 600 | H74: 4.6 | I74: открыть | J74: ferrari f1 t shirt
A75: футболка | B75: — | C75: своя печать | D75: Customized Printed Leisure T-Shirt Tee DIY Your Own Design Like Photo Or Logo T Shirt Fashion Custom Men's Tops Tshirt Tees | E75: 793 | G75: 600 | H75: 4.7 | I75: открыть | J75: red bull racing t shirt
A76: поло | B76: — | C76: своя печать | D76: Summer Cheap Causal Polo Shirt Personal Company Group Logo Custom Print Embroidery Men and Women Custom Breathable polo shirts | E76: 1298 | F76: 1.09 | G76: 600 | H76: 4.3 | I76: открыть | J76: red bull racing t shirt
A77: футболка | B77: — | C77: своя печать | D77: Diy Add Your Own Custom Text Name Men's T Shirt Casual Dress High Quality Mens T-shirt 5xL Personalized Message Band Tshirts | E77: 530 | G77: 600 | H77: 4.8 | I77: открыть | J77: custom print t shirt heavyweight cotton
A78: кофта | B78: — | C78: своя печать | D78: Customized DIY Print Men Woman Autumn Winter Hoodies Casual Classic Pullovers Simple Comfy Streetwear Soft Warm Sports Clothing | E78: 2117 | F78: 5.82 | G78: 600 | H78: 4.4 | I78: открыть | J78: custom logo hoodie heavyweight
A79: кофта | B79: — | C79: своя печать | D79: 2024 New Fashion Your Own Design Brand Logo/Picture Personalized Custom Anywhere Men Women DIY Zipper cardigan hoodie | E79: 1479 | F79: 11.56 | G79: 600 | H79: 4.7 | I79: открыть | J79: custom logo hoodie heavyweight
A80: кофта | B80: — | C80: своя печать | D80: Custom Prints Men's Women's Hoodies Loose Casual Wear Solid Color Hoodies Long Sleeve Hooded Personality Streetwear Sweatshirts | E80: 1419 | G80: 600 | H80: 4.9 | I80: открыть | J80: custom logo hoodie heavyweight
A81: кепка | B81: — | C81: своя печать | D81: Custom Brand LOGO Personality DIY Print Trucker Hat For Kids Net Baseball Cap Men Women Blank Mesh Adjustable Sun Hat Visor Adjusts for all sizes 592 sold 4.7 | E81: 92 | G81: 592 | I81: открыть | J81: red bull racing cap
A82: кепка | B82: — | C82: своя печать | D82: Custom Logo Baseball Cap Text Photo Team Embroidery Bone Gorras Diy Casquette Snapback Hat For Men Women Stays vibrant, stylish 557 sold 4.8 | E82: 1027 | G82: 557 | I82: открыть | J82: red bull racing cap
A83: кепка | B83: Aston Martin | C83: логотип команды | D83: F1 Racing Team Aston Martin Daily Training Baseball Cap Fernando Alonso Men Outdoor Sunscreen Sun Hat Casual Fashion Peaked Cap | E83: 930 | F83: 4.57 | G83: 500 | H83: 4.7 | I83: открыть | J83: f1 cap
A84: кепка | B84: Aston Martin | C84: логотип команды | D84: Aston Martin F1 Team Fernando Alonso Baseball Cap for Unisex Adjustable for Snapback Hat Sporty Design Trendy Accessories | E84: 986 | F84: 1.85 | G84: 500 | H84: 4.8 | I84: открыть | J84: formula 1 baseball cap
A85: футболка | B85: — | C85: своя печать | D85: Custom Tshirt Front Back Print Professional Your Own Logo Text Photo Male Personalized Premium Gifts T-shirt EU Size 100% Cotton | E85: 1018 | F85: 6.09 | G85: 500 | H85: 4.8 | I85: открыть | J85: red bull racing t shirt
A86: кофта | B86: — | C86: нет F1 в названии | D86: Men Solid Crew Neck Sweatshirt Small Horse Rider Embroidery Soft Brushed Fleece Pullover Loose Fit Casual Daily Top Autumn Winte | E86: 922 | G86: 500 | H86: 3.3 | I86: открыть | J86: mclaren f1 t shirt
A87: футболка | B87: — | C87: своя печать | D87: 230g Heavy Men Women Washed Vintage Customized Print Oversized T-Shirts Street Hip Hop Punk Harajuku Casual Cotton Short EU Size | E87: 1644 | F87: 13.53 | G87: 500 | H87: 4.9 | I87: открыть | J87: custom print t shirt heavyweight cotton
A88: футболка | B88: — | C88: своя печать | D88: Free Custom T-shirt Printing Logo Image Work Clothes Diy Short Sleeved Top 100% Cotton Enterprise Embroidery Team Culture Shirt | E88: 539 | G88: 500 | H88: 4.7 | I88: открыть | J88: custom print t shirt heavyweight cotton
A89: футболка | B89: — | C89: нет F1 в названии | D89: Hide Your Wife, Alpha Werewolf Is Coming! Funny Werewolf Meme T-shirt, Trendy Casual Hip-hop Women's Short-sleeved Shirt.Y2K Top | E89: 1154 | F89: 0.99 | G89: 493 | H89: 4.2 | I89: открыть | J89: ferrari f1 t shirt
A90: футболка | B90: — | C90: своя печать | D90: Men's and Women's Cotton Washed T-Shirt Custom Printed T-Shirt 230G Top DIY Your Favorite Pattern or Logo Fashionable Custom Top | E90: 2020 | F90: 5.28 | G90: 490 | H90: 4.8 | I90: открыть | J90: custom print t shirt heavyweight cotton
A91: футболка | B91: — | C91: нет F1 в названии | D91: Men's short-sleeved t-shirt, printed with racing cars English graphics loose fit fashionable casual round neck top spring summer | E91: 1713 | F91: 3.56 | G91: 489 | H91: 4.5 | I91: открыть | J91: formula 1 t shirt men
A92: кепка | B92: — | C92: нет F1 в названии | D92: Hot Sale Unisex Baseball Cap Slight Curved Brim Style Trucker Hat Men & Women Casual Outdoor Breathable Summer Mesh Cap | E92: 666 | F92: 0.99 | G92: 486 | H92: 4.9 | I92: открыть | J92: mclaren f1 cap
A93: поло | B93: — | C93: своя печать | D93: Summer Quick-drying Polo Shirt Custom Print Logo Golf Jerseys Individual Group Personalized Custom Embroidery LOGO Polo Tees Top | E93: 874 | F93: 0.99 | G93: 473 | H93: 4.2 | I93: открыть | J93: ferrari f1 t shirt
A94: кепка | B94: — | C94: своя печать | D94: Custom Logo Solid Color Adjustable Baseball Caps For Men And Women Embroidery Print Logo Spring Summer Cotton Shade Snapback Cap | E94: 420 | G94: 459 | H94: 4.4 | I94: открыть | J94: custom logo embroidery baseball cap
A95: футболка | B95: — | C95: своя печать | D95: 100%cotton,Custom Children Colorful T-shirts DIY Print Your Design Kids T-shirts Boys/Girls Tee Shirts,Contact Seller Frist | E95: 912 | G95: 457 | H95: 4.9 | I95: открыть | J95: custom print t shirt heavyweight cotton
A96: кофта | B96: — | C96: нет F1 в названии | D96: 2026 New YAMAHA Logo Motorcycle Racing Race Retro Velvet Half Zipper Hoodie Men's Multi Pocket Autumn/Winter Casual Sweatshirt | E96: 1746 | G96: 442 | H96: 4.3 | I96: открыть | J96: f1 hoodie
A97: футболка | B97: Mercedes | C97: логотип команды | D97: For Mercedes Benz W177 W205 W204 W212 W213 W176 CLA Steering Wheel Top Centre Marker Made of Alcantara Car Interior Accessories | E97: 437 | F97: 1.09 | G97: 440 | H97: 4.6 | I97: открыть | J97: mercedes f1 t shirt
A98: кепка | B98: — | C98: своя печать | D98: EMROJENTIA Custom Embroidered Caps and Hats - Personalized Logo or Text- - Ideal for Business, Events, and Gifts | E98: 1276 | G98: 438 | H98: 4.7 | I98: открыть | J98: ferrari f1 cap
A99: футболка | B99: — | C99: своя печать | D99: Custom-made men's T-shirts are suitable for team gatherings, gyms, and sports cotton round-neck short-sleeved shirts | E99: 1699 | F99: 4.48 | G99: 438 | H99: 4.7 | I99: открыть | J99: custom print t shirt heavyweight cotton
A100: футболка | B100: Williams | C100: логотип команды | D100: 2025 New F1 Racing T-shirt Williams Fan Shirt Outdoor Sports Quick drying Breathable Cycling Top Men's Casual Street T-shirt | E100: 442 | G100: 437 | H100: 4.5 | I100: открыть | J100: f1 t shirt
A101: футболка | B101: — | C101: своя печать | D101: 100% Pure Cotton Round Neck Solid Color Short Sleeved Shirt, Free to Add Your Own Design Soft Casual T-shirt, Customized T-shirt | E101: 742 | F101: 2.81 | G101: 433 | H101: 4.9 | I101: открыть | J101: custom print t shirt heavyweight cotton
...

Sheet Постеры — размеры
A1: Постеры: цена по размерам
A2: Лот 1005005851892159: 21 дизайн, холст без рамки, цена одинакова для всех дизайнов. Оценка 4.4, 112 заказов. «На сайт» — какие размеры предлагать (по умолчанию 4 ходовых).
A4: Размер | B4: Цена на Ali, ₽ | C4: Наша цена, ₽ | D4: Прибыль с шт., ₽ | E4: На сайт
A5: 13×18 см | B5: 289 | C5: =IF(B5="","",IF(B5<Параметры!$B$4,CEILING(B5*Параметры!$B$5,100)-10,IF(B5<=Параметры!$B$6,CEILING(B5*Параметры!$B$7,100)-10,CEILING(B5*Параметры!$B$8,100)-10))) -> 590 | D5: =IF(B5="","",ROUND(C5*(1-Параметры!$B$9-Параметры!$B$10-Параметры!$B$11)-B5,0)) -> 215
A6: 15×20 см | B6: 379 | C6: =IF(B6="","",IF(B6<Параметры!$B$4,CEILING(B6*Параметры!$B$5,100)-10,IF(B6<=Параметры!$B$6,CEILING(B6*Параметры!$B$7,100)-10,CEILING(B6*Параметры!$B$8,100)-10))) -> 790 | D6: =IF(B6="","",ROUND(C6*(1-Параметры!$B$9-Параметры!$B$10-Параметры!$B$11)-B6,0)) -> 296
A7: 20×25 см | B7: 472 | C7: =IF(B7="","",IF(B7<Параметры!$B$4,CEILING(B7*Параметры!$B$5,100)-10,IF(B7<=Параметры!$B$6,CEILING(B7*Параметры!$B$7,100)-10,CEILING(B7*Параметры!$B$8,100)-10))) -> 990 | D7: =IF(B7="","",ROUND(C7*(1-Параметры!$B$9-Параметры!$B$10-Параметры!$B$11)-B7,0)) -> 374
A8: 20×30 см | B8: 519 | C8: =IF(B8="","",IF(B8<Параметры!$B$4,CEILING(B8*Параметры!$B$5,100)-10,IF(B8<=Параметры!$B$6,CEILING(B8*Параметры!$B$7,100)-10,CEILING(B8*Параметры!$B$8,100)-10))) -> 1090 | D8: =IF(B8="","",ROUND(C8*(1-Параметры!$B$9-Параметры!$B$10-Параметры!$B$11)-B8,0)) -> 413 | E8: да
A9: 30×40 см | B9: 629 | C9: =IF(B9="","",IF(B9<Параметры!$B$4,CEILING(B9*Параметры!$B$5,100)-10,IF(B9<=Параметры!$B$6,CEILING(B9*Параметры!$B$7,100)-10,CEILING(B9*Параметры!$B$8,100)-10))) -> 1290 | D9: =IF(B9="","",ROUND(C9*(1-Параметры!$B$9-Параметры!$B$10-Параметры!$B$11)-B9,0)) -> 474 | E9: да
A10: 40×50 см | B10: 829 | C10: =IF(B10="","",IF(B10<Параметры!$B$4,CEILING(B10*Параметры!$B$5,100)-10,IF(B10<=Параметры!$B$6,CEILING(B10*Параметры!$B$7,100)-10,CEILING(B10*Параметры!$B$8,100)-10))) -> 1690 | D10: =IF(B10="","",ROUND(C10*(1-Параметры!$B$9-Параметры!$B$10-Параметры!$B$11)-B10,0)) -> 616
A11: 40×60 см | B11: 931 | C11: =IF(B11="","",IF(B11<Параметры!$B$4,CEILING(B11*Параметры!$B$5,100)-10,IF(B11<=Параметры!$B$6,CEILING(B11*Параметры!$B$7,100)-10,CEILING(B11*Параметры!$B$8,100)-10))) -> 1890 | D11: =IF(B11="","",ROUND(C11*(1-Параметры!$B$9-Параметры!$B$10-Параметры!$B$11)-B11,0)) -> 685 | E11: да
A12: 50×70 см | B12: 1052 | C12: =IF(B12="","",IF(B12<Параметры!$B$4,CEILING(B12*Параметры!$B$5,100)-10,IF(B12<=Параметры!$B$6,CEILING(B12*Параметры!$B$7,100)-10,CEILING(B12*Параметры!$B$8,100)-10))) -> 2190 | D12: =IF(B12="","",ROUND(C12*(1-Параметры!$B$9-Параметры!$B$10-Параметры!$B$11)-B12,0)) -> 820 | E12: да
A13: 60×80 см | B13: 1269 | C13: =IF(B13="","",IF(B13<Параметры!$B$4,CEILING(B13*Параметры!$B$5,100)-10,IF(B13<=Параметры!$B$6,CEILING(B13*Параметры!$B$7,100)-10,CEILING(B13*Параметры!$B$8,100)-10))) -> 2590 | D13: =IF(B13="","",ROUND(C13*(1-Параметры!$B$9-Параметры!$B$10-Параметры!$B$11)-B13,0)) -> 945
A14: 60×90 см | B14: 1372 | C14: =IF(B14="","",IF(B14<Параметры!$B$4,CEILING(B14*Параметры!$B$5,100)-10,IF(B14<=Параметры!$B$6,CEILING(B14*Параметры!$B$7,100)-10,CEILING(B14*Параметры!$B$8,100)-10))) -> 2790 | D14: =IF(B14="","",ROUND(C14*(1-Параметры!$B$9-Параметры!$B$10-Параметры!$B$11)-B14,0)) -> 1013
A16: Дизайны
A17: SKU-1 | B17: McLaren M23
A18: SKU-2 | B18: McLaren-Mercedes MP4-23
A19: SKU-3 | B19: McLaren MCL34
A20: SKU-4 | B20: Lotus 98T
A21: SKU-5 | B21: Red Bull Racing RB16
A22: SKU-6 | B22: Lotus 99T
A23: SKU-7 | B23: Jordan 191
A24: SKU-8 | B24: Mercedes AMG W10
A25: SKU-9 | B25: McLaren MP4/5B
A26: SKU-10 | B26: McLaren MP4/4
A27: SKU-11 | B27: McLaren MP4/6
A28: SKU-12 | B28: Brawn BGP001
... A37: SKU-21 | B37: Schumacher / Ferrari (японский стиль)

Sheet Варианты AliExpress
A1: Все варианты моделей из лотов (CSV из Chrome, 25.09.2026)
A2: «В ассортименте» — вариант взят на лист «Ассортимент». «Дубль» — такой же есть дешевле или с бо́льшим числом заказов. «Убрано» — версии, которые решили не брать.
A4: Лот | B4: Вариант на Ali | C4: Болид | D4: Пилот | E4: Ливрея / версия | F4: Год | G4: Масштаб | H4: Цена, ₽ | I4: Рейтинг | J4: Заказов | K4: Статус
A5: 1005010208916818 | B5: 1-VER-Japan | C5: Red Bull RB21 | D5: Ферстаппен #1 | E5: белая, ГП Японии | F5: 2025 | G5: 1:43 | H5: 789 | I5: 4.9 | J5: 1947 | K5: в ассортименте
A6: 1005010208916818 | B6: 22-TSU-Japan | C6: Red Bull RB21 | D6: Цунода #22 | E6: белая, ГП Японии | F6: 2025 | G6: 1:43 | H6: 789 | I6: 4.9 | J6: 1947 | K6: в ассортименте
A7: 1005010208916818 | B7: 22-TSU-Bahrain | C7: Red Bull RB21 | D7: Цунода #22 | E7: стандартная | F7: 2025 | G7: 1:43 | H7: 789 | I7: 4.9 | J7: 1947 | K7: в ассортименте
A8: 1005010208916818 | B8: 16-LEC | C8: Ferrari SF-25 | D8: Леклер #16 | E8: стандартная | F8: 2025 | G8: 1:43 | H8: 789 | I8: 4.9 | J8: 1947 | K8: в ассортименте
A9: 1005010208916818 | B9: 81-PIA-Australia | C9: McLaren MCL39 | D9: Пиастри #81 | E9: ГП Австралии | F9: 2025 | G9: 1:43 | H9: 789 | I9: 4.9 | J9: 1947 | K9: убрано: версия «Австралия»
A10: 1005010208916818 | B10: 63-RUS-Australia | C10: Mercedes W16 | D10: Рассел #63 | E10: ГП Австралии | F10: 2025 | G10: 1:43 | H10: 789 | I10: 4.9 | J10: 1947 | K10: убрано: версия «Австралия»
A11: 1005010208916818 | B11: 16-LEC-Miami | C11: Ferrari SF-25 | D11: Леклер #16 | E11: ГП Майами | F11: 2025 | G11: 1:43 | H11: 789 | I11: 4.9 | J11: 1947 | K11: в ассортименте
A12: 1005010208916818 | B12: 44-HAM-Miami | C12: Ferrari SF-25 | D12: Хэмилтон #44 | E12: ГП Майами | F12: 2025 | G12: 1:43 | H12: 789 | I12: 4.9 | J12: 1947 | K12: в ассортименте
A13: 1005010208916818 | B13: 4-NOR-Britain | C13: McLaren MCL39 | D13: Норрис #4 | E13: ГП Великобритании | F13: 2025 | G13: 1:43 | H13: 789 | I13: 4.9 | J13: 1947 | K13: убрано: ливрея «Великобритания»
A14: 1005010208916818 | B14: 81-PIA-Britain | C14: McLaren MCL39 | D14: Пиастри #81 | E14: ГП Великобритании | F14: 2025 | G14: 1:43 | H14: 789 | I14: 4.9 | J14: 1947 | K14: убрано: ливрея «Великобритания»
A15: 1005010208916818 | B15: 63-RUS-Britain | C15: Mercedes W16 | D15: Рассел #63 | E15: ГП Великобритании | F15: 2025 | G15: 1:43 | H15: 789 | I15: 4.9 | J15: 1947 | K15: убрано: ливрея «Великобритания»
A16: 1005010208755468 | B16: 2025 SF25-16 | C16: Ferrari SF-25 | D16: Леклер #16 | E16: стандартная | F16: 2025 | G16: 1:43 | H16: 879 | I16: 4.9 | J16: 791 | K16: дубль: берём лот …916818 за 789 ₽
... A61: 1005010633502926 | B61: 1-24 2024 SF24-55 | C61: Ferrari SF-24 | D61: Сайнс #55 | E61: стандартная | F61: 2024 | G61: 1:24 | H61: 2439 | I61: 4.9 | J61: 78 | K61: в ассортименте

Sheet Что уточнить
A1: Что осталось проверить
A3: Конструкторы CaDA 1:24 (2 лота) | B3: Цена нужного варианта, официальный магазин CaDA, число деталей и возраст на коробке. В CSV из Chrome этих лотов нет, цены — из поиска aliexpress.com: там была только цена для новых покупателей, в таблице — зачёркнутая как верхняя оценка. Реальная может быть до двух раз ниже.
A4: Реплики 1:8 (7 машин, 5 лотов) | B4: Цена нужного варианта и вариант «с коробкой»; фото коробки в отзывах: без логотипа LEGO, печать нормального качества. Жёлтые цены — верхняя оценка.
A5: Доставка | B5: Цены в таблице — за товар. Если доставка в РФ платная, прибавить её к цене на Ali.
A6: Новинки 2026 (1:43) | B6: Оценок нет, 31–45 заказов. Сначала заказать по одной для проверки качества.
A7: Мерч в стиле командной формы | B7: Цена нужного размера (жёлтые — верхняя оценка), фото из отзывов: качество печати и вышивки. Кепки и худи Ferrari, Red Bull, Mercedes, McLaren поискать на aliexpress.ru — на aliexpress.com их почти нет.
A8: Мерч — размеры | B8: У каждого продавца одежды взять таблицу размеров в сантиметрах: азиатская сетка обычно на 1–2 размера меньше.
A9: Постеры | B9: Оценка лота 4.4 — ниже остальных; посмотреть фото печати в отзывах.

Sheet Параметры
A1: Параметры расчёта
A2: Синие ячейки можно менять — цены и прибыль на листах «Ассортимент» и «Постеры — размеры» пересчитаются.
A4: Порог 1: закупка дешевле, ₽ | B4: 1500 | C4: Правило наценки из f1-shop/01-business-model.md
A5: Наценка до порога 1, × | B5: 2 | C5: Дешёвые позиции: ×2
A6: Порог 2: закупка до, ₽ | B6: 7000
A7: Наценка между порогами, × | B7: 1.6 | C7: Средние позиции: ×1,6
A8: Наценка дороже порога 2, × | B8: 1.35 | C8: Дорогие позиции: ×1,35
A9: Эквайринг, доля | B9: 0.035 | C9: ЮKassa, карта; по СБП меньше (f1-shop/03-payments.md)
A10: Налог УСН «Доходы», доля | B10: 0.06 | C10: ИП на УСН 6 %
A11: Резерв на возвраты, доля | B11: 0.05 | C11: f1-shop/01-business-model.md
A12: Лимит цены для 1:24, ₽ | B12: 2800 | C12: Правило владельца магазина: 1:24 берём до 2 800 ₽
A13: Курс доллара, ₽ | B13: 84.2 | C13: ЦБ РФ на 20.09.2026 — для лотов с aliexpress.com (конструкторы, мерч)
A14: Резерв на возвраты, одежда, доля | B14: 0.1 | C14: По одежде возвратов больше — размер (f1-shop/10-content.md)
